Workbook

Sheet Resource
A1: 年 | B1: 月份 | C1: 期間資料版本 | D1: 公司 | E1: 事業單位 | F1: 作業中心 | G1: 作業中心-第一階 | H1: 作業中心-第二階 | I1: 可控制/不可控制之資源 | J1: 成本類型 | K1: 停止分攤 | L1: 資源代碼 | M1: 資源-第一階 | N1: 金額 | O1: 資源動因 | P1: 動因簡述 | Q1: 資源動因值 | R1: (受)支援作業中心 | S1: 價值標的類型 | T1: 價值標的代碼 | U1: 資源動因費率
A2: 2018 | B2: 3 | C2: 201803 | D2: Kelly Group | E2: 公隆化學股份有限公司 | F2: NASL10:新事業開發部 | G2: NASL10:新事業開發部 | I2: 可控制之資源 | J2: 1.作業中心自用之資源 | K2: False | L2: R02 | M2: 差旅費用 | N2: 130000 | O2: (DirectAssigned) | P2: (直接歸屬)
A3: 2018 | B3: 3 | C3: 201803 | D3: Kelly Group | E3: 公隆化學股份有限公司 | F3: NASL11:製程化學課 | G3: NASL10:新事業開發部 | H3: NASL11:製程化學課 | I3: 可控制之資源 | J3: 1.作業中心自用之資源 | K3: True | L3: R02 | M3: 差旅費用 | N3: 40342 | O3: (DirectAssigned) | P3: (直接歸屬)
A4: 2018 | B4: 3 | C4: 201803 | D4: Kelly Group | E4: 公隆化學股份有限公司 | F4: NASL12:電子化學課 | G4: NASL10:新事業開發部 | H4: NASL12:電子化學課 | I4: 可控制之資源 | J4: 1.作業中心自用之資源 | K4: True | L4: R02 | M4: 差旅費用 | N4: 61118 | O4: (DirectAssigned) | P4: (直接歸屬)
A5: 2018 | B5: 3 | C5: 201803 | D5: Kelly Group | E5: 公隆化學股份有限公司 | F5: NASL11:製程化學課 | G5: NASL10:新事業開發部 | H5: NASL11:製程化學課 | I5: 不可控制之資源 | J5: 5.支援作業中心(SSU)分攤之資源 | K5: True | L5: R01 | M5: 薪資費用 | N5: 218161 | O5: (ByDriverValue) | P5: (設定比率) | Q5: 1 | R5: NATC11:應用技術課 | U5: 218161
A6: 2018 | B6: 3 | C6: 201803 | D6: Kelly Group | E6: 公隆化學股份有限公司 | F6: NASL11:製程化學課 | G6: NASL10:新事業開發部 | H6: NASL11:製程化學課 | I6: 不可控制之資源 | J6: 4.管理作業中心分攤之資源 | K6: True | L6: R02 | M6: 差旅費用 | N6: 104000 | O6: (ByDriverValue) | P6: (設定比率) | Q6: 0.8 | R6: NASL10:新事業開發部 | U6: 130000
A7: 2018 | B7: 3 | C7: 201803 | D7: Kelly Group | E7: 公隆化學股份有限公司 | F7: NASL12:電子化學課 | G7: NASL10:新事業開發部 | H7: NASL12:電子化學課 | I7: 不可控制之資源 | J7: 4.管理作業中心分攤之資源 | K7: True | L7: R02 | M7: 差旅費用 | N7: 26000 | O7: (ByDriverValue) | P7: (設定比率) | Q7: 0.2 | R7: NASL10:新事業開發部 | U7: 130000
A8: 2018 | B8: 3 | C8: 201803 | D8: Kelly Group | E8: 公隆化學股份有限公司 | F8: NASL11:製程化學課 | G8: NASL10:新事業開發部 | H8: NASL11:製程化學課 | I8: 可控制之資源 | J8: 1.作業中心自用之資源 | K8: True | L8: R01 | M8: 薪資費用 | N8: 71367 | O8: (DirectAssigned) | P8: (直接歸屬)
A9: 2018 | B9: 3 | C9: 201803 | D9: Kelly Group | E9: 公隆化學股份有限公司 | F9: NATC11:應用技術課 | G9: NASL10:新事業開發部 | H9: NATC11:應用技術課 | I9: 可控制之資源 | J9: 1.作業中心自用之資源 | K9: False | L9: R01 | M9: 薪資費用 | N9: 218161 | O9: (DirectAssigned) | P9: (直接歸屬)
A10: 2018 | B10: 3 | C10: 201803 | D10: Kelly Group | E10: 公隆化學股份有限公司 | F10: NASL12:電子化學課 | G10: NASL10:新事業開發部 | H10: NASL12:電子化學課 | I10: 可控制之資源 | J10: 1.作業中心自用之資源 | K10: True | L10: R01 | M10: 薪資費用 | N10: 125323 | O10: (DirectAssigned) | P10: (直接歸屬)
A11: 2018 | B11: 3 | C11: 201803 | D11: Kelly Group | E11: 公隆化學股份有限公司 | F11: NASL11:製程化學課 | G11: NASL10:新事業開發部 | H11: NASL11:製程化學課 | I11: 可控制之資源 | J11: 2.價值標的使用之資源 | K11: True | L11: R03 | M11: 交際費用 | N11: 300 | O11: (DirectAssigned) | P11: (直接歸屬) | S11: CustomerProject | T11: CPCRM00696:專案-健達生物
A12: 2018 | B12: 3 | C12: 201803 | D12: Kelly Group | E12: 公隆化學股份有限公司 | F12: NASL11:製程化學課 | G12: NASL10:新事業開發部 | H12: NASL11:製程化學課 | I12: 可控制之資源 | J12: 2.價值標的使用之資源 | K12: True | L12: R04 | M12: 樣品費用 | N12: 6350 | O12: (DirectAssigned) | P12: (直接歸屬) | S12: CustomerProject | T12: CPCRM00696:專案-健達生物
A13: 2018 | B13: 3 | C13: 201803 | D13: Kelly Group | E13: 公隆化學股份有限公司 | F13: NASL11:製程化學課 | G13: NASL10:新事業開發部 | H13: NASL11:製程化學課 | I13: 可控制之資源 | J13: 2.價值標的使用之資源 | K13: True | L13: R04 | M13: 樣品費用 | N13: 3372 | O13: (DirectAssigned) | P13: (直接歸屬) | S13: CustomerProject | T13: CPCRM00911:專案-台灣鉅邁
A14: 2018 | B14: 3 | C14: 201803 | D14: Kelly Group | E14: 公隆化學股份有限公司 | F14: NASL12:電子化學課 | G14: NASL10:新事業開發部 | H14: NASL12:電子化學課 | I14: 可控制之資源 | J14: 2.價值標的使用之資源 | K14: True | L14: R03 | M14: 交際費用 | N14: 1035 | O14: (DirectAssigned) | P14: (直接歸屬) | S14: CustomerProject | T14: CPCRM05498:專案-興勤電子
A15: 2018 | B15: 3 | C15: 201803 | D15: Kelly Group | E15: 公隆化學股份有限公司 | F15: NASL12:電子化學課 | G15: NASL10:新事業開發部 | H15: NASL12:電子化學課 | I15: 可控制之資源 | J15: 2.價值標的使用之資源 | K15: True | L15: R03 | M15: 交際費用 | N15: 3526 | O15: (DirectAssigned) | P15: (直接歸屬) | S15: CustomerProject | T15: CPCRM10848:專案-華新科技
A16: 2018 | B16: 3 | C16: 201803 | D16: Kelly Group | E16: 公隆化學股份有限公司 | F16: NASL12:電子化學課 | G16: NASL10:新事業開發部 | H16: NASL12:電子化學課 | I16: 可控制之資源 | J16: 2.價值標的使用之資源 | K16: True | L16: R03 | M16: 交際費用 | N16: 8493 | O16: (DirectAssigned) | P16: (直接歸屬) | S16: CustomerProject | T16: CPCRM11533:專案-國巨楠梓
A17: 2018 | B17: 3 | C17: 201803 | D17: Kelly Group | E17: 公隆化學股份有限公司 | F17: NASL11:製程化學課 | G17: NASL10:新事業開發部 | H17: NASL11:製程化學課 | I17: 可控制之資源 | J17: 2.價值標的使用之資源 | K17: True | L17: R05 | M17: 其他費用 | N17: 24210 | O17: (DirectAssigned) | P17: (直接歸屬) | S17: CustomerProject | T17: CPunknow:專案-未分析顧客
A18: 2018 | B18: 3 | C18: 201803 | D18: Kelly Group | E18: 公隆化學股份有限公司 | F18: NASL10:新事業開發部 | G18: NASL10:新事業開發部 | I18: 可控制之資源 | J18: 2.價值標的使用之資源 | K18: True | L18: R05 | M18: 其他費用 | N18: 3092 | O18: (DirectAssigned) | P18: (直接歸屬) | S18: CustomerProject | T18: CPunknow:專案-未分析顧客
A19: 2018 | B19: 3 | C19: 201803 | D19: Kelly Group | E19: 公隆化學股份有限公司 | F19: NASL12:電子化學課 | G19: NASL10:新事業開發部 | H19: NASL12:電子化學課 | I19: 可控制之資源 | J19: 2.價值標的使用之資源 | K19: True | L19: R05 | M19: 其他費用 | N19: 16648 | O19: (DirectAssigned) | P19: (直接歸屬) | S19: CustomerProject | T19: CPunknow:專案-未分析顧客
A20: 2018 | B20: 4 | C20: 201804 | D20: Kelly Group | E20: 公隆化學股份有限公司 | F20: NASL11:製程化學課 | G20: NASL10:新事業開發部 | H20: NASL11:製程化學課 | I20: 可控制之資源 | J20: 2.價值標的使用之資源 | K20: True | L20: R05 | M20: 其他費用 | N20: 3500 | O20: (DirectAssigned) | P20: (直接歸屬) | S20: CustomerProject | T20: CPCRM00400:專案-東隆五金
A21: 2018 | B21: 4 | C21: 201804 | D21: Kelly Group | E21: 公隆化學股份有限公司 | F21: NASL11:製程化學課 | G21: NASL10:新事業開發部 | H21: NASL11:製程化學課 | I21: 可控制之資源 | J21: 2.價值標的使用之資源 | K21: True | L21: R05 | M21: 其他費用 | N21: 1500 | O21: (DirectAssigned) | P21: (直接歸屬) | S21: CustomerProject | T21: CP華震科技:專案-華震科技
A22: 2018 | B22: 4 | C22: 201804 | D22: Kelly Group | E22: 公隆化學股份有限公司 | F22: NASL12:電子化學課 | G22: NASL10:新事業開發部 | H22: NASL12:電子化學課 | I22: 可控制之資源 | J22: 2.價值標的使用之資源 | K22: True | L22: R05 | M22: 其他費用 | N22: 1600 | O22: (DirectAssigned) | P22: (直接歸屬) | S22: CustomerProject | T22: CPCRM10848:專案-華新科技
A23: 2018 | B23: 4 | C23: 201804 | D23: Kelly Group | E23: 公隆化學股份有限公司 | F23: NASL12:電子化學課 | G23: NASL10:新事業開發部 | H23: NASL12:電子化學課 | I23: 可控制之資源 | J23: 2.價值標的使用之資源 | K23: True | L23: R03 | M23: 交際費用 | N23: 535 | O23: (DirectAssigned) | P23: (直接歸屬) | S23: CustomerProject | T23: CPCRM17381:專案-桃園-愛賽克
A24: 2018 | B24: 4 | C24: 201804 | D24: Kelly Group | E24: 公隆化學股份有限公司 | F24: NASL12:電子化學課 | G24: NASL10:新事業開發部 | H24: NASL12:電子化學課 | I24: 可控制之資源 | J24: 2.價值標的使用之資源 | K24: True | L24: R05 | M24: 其他費用 | N24: 3500 | O24: (DirectAssigned) | P24: (直接歸屬) | S24: CustomerProject | T24: CPCRM19822:專案-友達
A25: 2018 | B25: 4 | C25: 201804 | D25: Kelly Group | E25: 公隆化學股份有限公司 | F25: NASL12:電子化學課 | G25: NASL10:新事業開發部 | H25: NASL12:電子化學課 | I25: 可控制之資源 | J25: 2.價值標的使用之資源 | K25: True | L25: R05 | M25: 其他費用 | N25: 5409 | O25: (DirectAssigned) | P25: (直接歸屬) | S25: CustomerProject | T25: CPunknow:專案-未分析顧客
A26: 2018 | B26: 4 | C26: 201804 | D26: Kelly Group | E26: 公隆化學股份有限公司 | F26: NASL10:新事業開發部 | G26: NASL10:新事業開發部 | I26: 可控制之資源 | J26: 2.價值標的使用之資源 | K26: True | L26: R05 | M26: 其他費用 | N26: 3991 | O26: (DirectAssigned) | P26: (直接歸屬) | S26: CustomerProject | T26: CPunknow:專案-未分析顧客
A27: 2018 | B27: 4 | C27: 201804 | D27: Kelly Group | E27: 公隆化學股份有限公司 | F27: NASL11:製程化學課 | G27: NASL10:新事業開發部 | H27: NASL11:製程化學課 | I27: 可控制之資源 | J27: 2.價值標的使用之資源 | K27: True | L27: R05 | M27: 其他費用 | N27: 11664 | O27: (DirectAssigned) | P27: (直接歸屬) | S27: CustomerProject | T27: CPunknow:專案-未分析顧客
A28: 2018 | B28: 4 | C28: 201804 | D28: Kelly Group | E28: 公隆化學股份有限公司 | F28: NASL11:製程化學課 | G28: NASL10:新事業開發部 | H28: NASL11:製程化學課 | I28: 可控制之資源 | J28: 2.價值標的使用之資源 | K28: True | L28: R05 | M28: 其他費用 | N28: 1467 | O28: (DirectAssigned) | P28: (直接歸屬) | S28: CustomerProject | T28: CPEMERSON:專案-EMERSON
A29: 2018 | B29: 4 | C29: 201804 | D29: Kelly Group | E29: 公隆化學股份有限公司 | F29: NASL11:製程化學課 | G29: NASL10:新事業開發部 | H29: NASL11:製程化學課 | I29: 可控制之資源 | J29: 1.作業中心自用之資源 | K29: True | L29: R01 | M29: 薪資費用 | N29: 106463 | O29: (DirectAssigned) | P29: (直接歸屬)
A30: 2018 | B30: 4 | C30: 201804 | D30: Kelly Group | E30: 公隆化學股份有限公司 | F30: NATC11:應用技術課 | G30: NASL10:新事業開發部 | H30: NATC11:應用技術課 | I30: 可控制之資源 | J30: 1.作業中心自用之資源 | K30: False | L30: R01 | M30: 薪資費用 | N30: 268081 | O30: (DirectAssigned) | P30: (直接歸屬)
A31: 2018 | B31: 4 | C31: 201804 | D31: Kelly Group | E31: 公隆化學股份有限公司 | F31: NASL12:電子化學課 | G31: NASL10:新事業開發部 | H31: NASL12:電子化學課 | I31: 可控制之資源 | J31: 1.作業中心自用之資源 | K31: True | L31: R01 | M31: 薪資費用 | N31: 135850 | O31: (DirectAssigned) | P31: (直接歸屬)
A32: 2018 | B32: 4 | C32: 201804 | D32: Kelly Group | E32: 公隆化學股份有限公司 | F32: NASL11:製程化學課 | G32: NASL10:新事業開發部 | H32: NASL11:製程化學課 | I32: 不可控制之資源 | J32: 5.支援作業中心(SSU)分攤之資源 | K32: True | L32: R01 | M32: 薪資費用 | N32: 268081 | O32: (ByDriverValue) | P32: (設定比率) | Q32: 1 | R32: NATC11:應用技術課 | U32: 268081
A33: 2018 | B33: 4 | C33: 201804 | D33: Kelly Group | E33: 公隆化學股份有限公司 | F33: NASL11:製程化學課 | G33: NASL10:新事業開發部 | H33: NASL11:製程化學課 | I33: 不可控制之資源 | J33: 4.管理作業中心分攤之資源 | K33: True | L33: R02 | M33: 差旅費用 | N33: 104000 | O33: (ByDriverValue) | P33: (設定比率) | Q33: 0.8 | R33: NASL10:新事業開發部 | U33: 130000
A34: 2018 | B34: 4 | C34: 201804 | D34: Kelly Group | E34: 公隆化學股份有限公司 | F34: NASL12:電子化學課 | G34: NASL10:新事業開發部 | H34: NASL12:電子化學課 | I34: 不可控制之資源 | J34: 4.管理作業中心分攤之資源 | K34: True | L34: R02 | M34: 差旅費用 | N34: 26000 | O34: (ByDriverValue) | P34: (設定比率) | Q34: 0.2 | R34: NASL10:新事業開發部 | U34: 130000
A35: 2018 | B35: 4 | C35: 201804 | D35: Kelly Group | E35: 公隆化學股份有限公司 | F35: NASL10:新事業開發部 | G35: NASL10:新事業開發部 | I35: 可控制之資源 | J35: 1.作業中心自用之資源 | K35: False | L35: R02 | M35: 差旅費用 | N35: 130000 | O35: (DirectAssigned) | P35: (直接歸屬)
A36: 2018 | B36: 4 | C36: 201804 | D36: Kelly Group | E36: 公隆化學股份有限公司 | F36: NASL11:製程化學課 | G36: NASL10:新事業開發部 | H36: NASL11:製程化學課 | I36: 可控制之資源 | J36: 1.作業中心自用之資源 | K36: True | L36: R02 | M36: 差旅費用 | N36: 171828 | O36: (DirectAssigned) | P36: (直接歸屬)
A37: 2018 | B37: 4 | C37: 201804 | D37: Kelly Group | E37: 公隆化學股份有限公司 | F37: NASL12:電子化學課 | G37: NASL10:新事業開發部 | H37: NASL12:電子化學課 | I37: 可控制之資源 | J37: 1.作業中心自用之資源 | K37: True | L37: R02 | M37: 差旅費用 | N37: 39822 | O37: (DirectAssigned) | P37: (直接歸屬)
A38: 2018 | B38: 5 | C38: 201805 | D38: Kelly Group | E38: 公隆化學股份有限公司 | F38: NASL10:新事業開發部 | G38: NASL10:新事業開發部 | I38: 可控制之資源 | J38: 1.作業中心自用之資源 | K38: False | L38: R02 | M38: 差旅費用 | N38: 130000 | O38: (DirectAssigned) | P38: (直接歸屬)
A39: 2018 | B39: 5 | C39: 201805 | D39: Kelly Group | E39: 公隆化學股份有限公司 | F39: NASL11:製程化學課 | G39: NASL10:新事業開發部 | H39: NASL11:製程化學課 | I39: 可控制之資源 | J39: 1.作業中心自用之資源 | K39: True | L39: R02 | M39: 差旅費用 | N39: 86278 | O39: (DirectAssigned) | P39: (直接歸屬)
A40: 2018 | B40: 5 | C40: 201805 | D40: Kelly Group | E40: 公隆化學股份有限公司 | F40: NASL12:電子化學課 | G40: NASL10:新事業開發部 | H40: NASL12:電子化學課 | I40: 不可控制之資源 | J40: 4.管理作業中心分攤之資源 | K40: True | L40: R02 | M40: 差旅費用 | N40: 26000 | O40: (ByDriverValue) | P40: (設定比率) | Q40: 0.2 | R40: NASL10:新事業開發部 | U40: 130000
A41: 2018 | B41: 5 | C41: 201805 | D41: Kelly Group | E41: 公隆化學股份有限公司 | F41: NASL11:製程化學課 | G41: NASL10:新事業開發部 | H41: NASL11:製程化學課 | I41: 不可控制之資源 | J41: 4.管理作業中心分攤之資源 | K41: True | L41: R02 | M41: 差旅費用 | N41: 104000 | O41: (ByDriverValue) | P41: (設定比率) | Q41: 0.8 | R41: NASL10:新事業開發部 | U41: 130000
A42: 2018 | B42: 5 | C42: 201805 | D42: Kelly Group | E42: 公隆化學股份有限公司 | F42: NASL11:製程化學課 | G42: NASL10:新事業開發部 | H42: NASL11:製程化學課 | I42: 不可控制之資源 | J42: 5.支援作業中心(SSU)分攤之資源 | K42: True | L42: R01 | M42: 薪資費用 | N42: 239124 | O42: (ByDriverValue) | P42: (設定比率) | Q42: 1 | R42: NATC11:應用技術課 | U42: 239124
A43: 2018 | B43: 5 | C43: 201805 | D43: Kelly Group | E43: 公隆化學股份有限公司 | F43: NASL11:製程化學課 | G43: NASL10:新事業開發部 | H43: NASL11:製程化學課 | I43: 可控制之資源 | J43: 1.作業中心自用之資源 | K43: True | L43: R01 | M43: 薪資費用 | N43: 95428 | O43: (DirectAssigned) | P43: (直接歸屬)
A44: 2018 | B44: 5 | C44: 201805 | D44: Kelly Group | E44: 公隆化學股份有限公司 | F44: NATC11:應用技術課 | G44: NASL10:新事業開發部 | H44: NATC11:應用技術課 | I44: 可控制之資源 | J44: 1.作業中心自用之資源 | K44: False | L44: R01 | M44: 薪資費用 | N44: 239124 | O44: (DirectAssigned) | P44: (直接歸屬)
A45: 2018 | B45: 5 | C45: 201805 | D45: Kelly Group | E45: 公隆化學股份有限公司 | F45: NASL12:電子化學課 | G45: NASL10:新事業開發部 | H45: NASL12:電子化學課 | I45: 可控制之資源 | J45: 1.作業中心自用之資源 | K45: True | L45: R01 | M45: 薪資費用 | N45: 136807 | O45: (DirectAssigned) | P45: (直接歸屬)
A46: 2018 | B46: 5 | C46: 201805 | D46: Kelly Group | E46: 公隆化學股份有限公司 | F46: NASL11:製程化學課 | G46: NASL10:新事業開發部 | H46: NASL11:製程化學課 | I46: 可控制之資源 | J46: 2.價值標的使用之資源 | K46: True | L46: R05 | M46: 其他費用 | N46: 4000 | O46: (DirectAssigned) | P46: (直接歸屬) | S46: CustomerProject | T46: CPCRM00400:專案-東隆五金
A47: 2018 | B47: 5 | C47: 201805 | D47: Kelly Group | E47: 公隆化學股份有限公司 | F47: NASL11:製程化學課 | G47: NASL10:新事業開發部 | H47: NASL11:製程化學課 | I47: 可控制之資源 | J47: 2.價值標的使用之資源 | K47: True | L47: R04 | M47: 樣品費用 | N47: 4408 | O47: (DirectAssigned) | P47: (直接歸屬) | S47: CustomerProject | T47: CPCRM00696:專案-健達生物
A48: 2018 | B48: 5 | C48: 201805 | D48: Kelly Group | E48: 公隆化學股份有限公司 | F48: NASL11:製程化學課 | G48: NASL10:新事業開發部 | H48: NASL11:製程化學課 | I48: 可控制之資源 | J48: 2.價值標的使用之資源 | K48: True | L48: R04 | M48: 樣品費用 | N48: 2828 | O48: (DirectAssigned) | P48: (直接歸屬) | S48: CustomerProject | T48: CPCRM00911:專案-台灣鉅邁
A49: 2018 | B49: 5 | C49: 201805 | D49: Kelly Group | E49: 公隆化學股份有限公司 | F49: NASL11:製程化學課 | G49: NASL10:新事業開發部 | H49: NASL11:製程化學課 | I49: 可控制之資源 | J49: 2.價值標的使用之資源 | K49: True | L49: R05 | M49: 其他費用 | N49: 1500 | O49: (DirectAssigned) | P49: (直接歸屬) | S49: CustomerProject | T49: CPCRM01025:專案-典雅實業
A50: 2018 | B50: 5 | C50: 201805 | D50: Kelly Group | E50: 公隆化學股份有限公司 | F50: NASL11:製程化學課 | G50: NASL10:新事業開發部 | H50: NASL11:製程化學課 | I50: 可控制之資源 | J50: 2.價值標的使用之資源 | K50: True | L50: R05 | M50: 其他費用 | N50: 7974 | O50: (DirectAssigned) | P50: (直接歸屬) | S50: CustomerProject | T50: CPunknow:專案-未分析顧客
A51: 2018 | B51: 5 | C51: 201805 | D51: Kelly Group | E51: 公隆化學股份有限公司 | F51: NASL10:新事業開發部 | G51: NASL10:新事業開發部 | I51: 可控制之資源 | J51: 2.價值標的使用之資源 | K51: True | L51: R05 | M51: 其他費用 | N51: 366 | O51: (DirectAssigned) | P51: (直接歸屬) | S51: CustomerProject | T51: CPunknow:專案-未分析顧客
A52: 2018 | B52: 5 | C52: 201805 | D52: Kelly Group | E52: 公隆化學股份有限公司 | F52: NASL12:電子化學課 | G52: NASL10:新事業開發部 | H52: NASL12:電子化學課 | I52: 可控制之資源 | J52: 2.價值標的使用之資源 | K52: True | L52: R05 | M52: 其他費用 | N52: 18177 | O52: (DirectAssigned) | P52: (直接歸屬) | S52: CustomerProject | T52: CPunknow:專案-未分析顧客
A53: 2018 | B53: 5 | C53: 201805 | D53: Kelly Group | E53: 公隆化學股份有限公司 | F53: NASL10:新事業開發部 | G53: NASL10:新事業開發部 | I53: 可控制之資源 | J53: 2.價值標的使用之資源 | K53: True | L53: R05 | M53: 其他費用 | N53: 1541 | O53: (DirectAssigned) | P53: (直接歸屬) | S53: CustomerProject | T53: CP上海安捷:專案-上海安捷
A54: 2018 | B54: 5 | C54: 201805 | D54: Kelly Group | E54: 公隆化學股份有限公司 | F54: NASL10:新事業開發部 | G54: NASL10:新事業開發部 | I54: 可控制之資源 | J54: 2.價值標的使用之資源 | K54: True | L54: R05 | M54: 其他費用 | N54: 599 | O54: (DirectAssigned) | P54: (直接歸屬) | S54: CustomerProject | T54: CP上海安捷:專案-上海安捷

Sheet 可控不可控
A1: 停止分攤 | B1: True
A3: 加總 - 金額 | C3: 月份
A4: 作業中心 | B4: 可控制/不可控制之資源 | C4: 3 | D4: 4 | E4: 5 | F4: Grand Total
A5: NASL10:新事業開發部 | B5: 可控制之資源 | C5: 3092 | D5: 3991 | E5: 2506 | F5: 9589
A6: NASL11:製程化學課 | B6: 不可控制之資源 | C6: 322161 | D6: 372081 | E6: 343124 | F6: 1037366
B7: 可控制之資源 | C7: 145941 | D7: 296422 | E7: 202416 | F7: 644779
A8: NASL12:電子化學課 | B8: 不可控制之資源 | C8: 26000 | D8: 26000 | E8: 26000 | F8: 78000
B9: 可控制之資源 | C9: 216143 | D9: 186716 | E9: 154984 | F9: 557843
A10: Grand Total | C10: 713337 | D10: 885210 | E10: 729030 | F10: 2327577

Sheet 可控不可控 (2)
A1: 停止分攤 | B1: True
A3: 加總 - 金額 | D3: 月份
A4: 作業中心 | B4: 可控制/不可控制之資源 | C4: 資源-第一階 | D4: 3 | E4: 4 | F4: 5 | G4: Grand Total
A5: NASL10:新事業開發部 | B5: 可控制之資源 | C5: 其他費用 | D5: 3092 | E5: 3991 | F5: 2506 | G5: 9589
A6: NASL11:製程化學課 | B6: 不可控制之資源 | D6: 322161 | E6: 372081 | F6: 343124 | G6: 1037366
B7: 可控制之資源 | C7: 交際費用 | D7: 300 | G7: 300
C8: 其他費用 | D8: 24210 | E8: 18131 | F8: 13474 | G8: 55815
C9: 差旅費用 | D9: 40342 | E9: 171828 | F9: 86278 | G9: 298448
C10: 樣品費用 | D10: 9722 | F10: 7236 | G10: 16958
C11: 薪資費用 | D11: 71367 | E11: 106463 | F11: 95428 | G11: 273258
A12: NASL12:電子化學課 | B12: 不可控制之資源 | D12: 26000 | E12: 26000 | F12: 26000 | G12: 78000
B13: 可控制之資源 | C13: 交際費用 | D13: 13054 | E13: 535 | G13: 13589
C14: 其他費用 | D14: 16648 | E14: 10509 | F14: 18177 | G14: 45334
C15: 差旅費用 | D15: 61118 | E15: 39822 | G15: 100940
C16: 薪資費用 | D16: 125323 | E16: 135850 | F16: 136807 | G16: 397980
A17: Grand Total | D17: 713337 | E17: 885210 | F17: 729030 | G17: 2327577

Sheet ActivityCenter+ActivityModel
A1: 年 | B1: 月份 | C1: 期間資料版本 | D1: 公司 | E1: 事業單位 | F1: 作業中心-第一階 | G1: 作業中心-第二階 | H1: 成本類型 | I1: 金額 | J1: 作業中心動因費率 | K1: 作業中心動因值 | L1: 作業-第一階 | M1: 作業-第二階 | N1: 附加價值屬性 | O1: 顧客服務屬性
A2: 2018 | B2: 3 | C2: 201803 | D2: Kelly Group | E2: 公隆化學股份有限公司 | F2: NASL10:新事業開發部 | G2: NASL11:製程化學課 | H2: N. Cap. Rate*N. Cap. Hour | I2: 173548 | J2: 39.299819 | K2: 4416 | L2: N01:取得顧客作業
A3: 2018 | B3: 3 | C3: 201803 | D3: Kelly Group | E3: 公隆化學股份有限公司 | F3: NASL10:新事業開發部 | G3: NASL12:電子化學課 | H3: N. Cap. Rate*N. Cap. Hour | I3: 106220.5 | J3: 9.6214221 | K3: 11040 | L3: N01:取得顧客作業
A4: 2018 | B4: 3 | C4: 201803 | D4: Kelly Group | E4: 公隆化學股份有限公司 | F4: NASL10:新事業開發部 | G4: NASL11:製程化學課 | H4: N. Cap. Rate*N. Cap. Hour | I4: 86774 | J4: 39.299819 | K4: 2208 | L4: N02:維持顧客作業
A5: 2018 | B5: 3 | C5: 201803 | D5: Kelly Group | E5: 公隆化學股份有限公司 | F5: NASL10:新事業開發部 | G5: NASL12:電子化學課 | H5: N. Cap. Rate*N. Cap. Hour | I5: 33990.56 | J5: 9.6214221 | K5: 3532.8 | L5: N02:維持顧客作業
A6: 2018 | B6: 3 | C6: 201803 | D6: Kelly Group | E6: 公隆化學股份有限公司 | F6: NASL10:新事業開發部 | G6: NASL11:製程化學課 | H6: N. Cap. Rate*N. Cap. Hour | I6: 130161 | J6: 39.299819 | K6: 3312 | L6: N03:售後服務作業
A7: 2018 | B7: 3 | C7: 201803 | D7: Kelly Group | E7: 公隆化學股份有限公司 | F7: NASL10:新事業開發部 | G7: NASL12:電子化學課 | H7: N. Cap. Rate*N. Cap. Hour | I7: 33990.56 | J7: 9.6214221 | K7: 3532.8 | L7: N03:售後服務作業
A8: 2018 | B8: 3 | C8: 201803 | D8: Kelly Group | E8: 公隆化學股份有限公司 | F8: NASL10:新事業開發部 | G8: NASL11:製程化學課 | H8: N. Cap. Rate*N. Cap. Hour | I8: 43387 | J8: 39.299819 | K8: 1104 | L8: N04:其他
A9: 2018 | B9: 3 | C9: 201803 | D9: Kelly Group | E9: 公隆化學股份有限公司 | F9: NASL10:新事業開發部 | G9: NASL12:電子化學課 | H9: N. Cap. Rate*N. Cap. Hour | I9: 38239.38 | J9: 9.6214221 | K9: 3974.4 | L9: N04:其他
A10: 2018 | B10: 3 | C10: 201803 | D10: Kelly Group | E10: 公隆化學股份有限公司 | F10: NASL10:新事業開發部 | G10: NASL11:製程化學課 | H10: A. Cap. Rate*A. Cap. Hour | I10: 8174.3623 | J10: 39.299819 | K10: 208 | L10: N02:維持顧客作業 | M10: A01:關係維護 | N10: 有附加價值 | O10: 維持成本
A11: 2018 | B11: 3 | C11: 201803 | D11: Kelly Group | E11: 公隆化學股份有限公司 | F11: NASL10:新事業開發部 | G11: NASL11:製程化學課 | H11: N. Cap. Rate*A. Cap. Hour | I11: 8174.3623 | J11: 39.299819 | K11: 208 | L11: N02:維持顧客作業 | M11: A01:關係維護 | N11: 有附加價值 | O11: 維持成本
A12: 2018 | B12: 3 | C12: 201803 | D12: Kelly Group | E12: 公隆化學股份有限公司 | F12: NASL10:新事業開發部 | G12: NASL12:電子化學課 | H12: A. Cap. Rate*A. Cap. Hour | I12: 5328.7876 | J12: 9.6014191 | K12: 555 | L12: N02:維持顧客作業 | M12: A01:關係維護 | N12: 有附加價值 | O12: 維持成本
A13: 2018 | B13: 3 | C13: 201803 | D13: Kelly Group | E13: 公隆化學股份有限公司 | F13: NASL10:新事業開發部 | G13: NASL12:電子化學課 | H13: N. Cap. Rate*A. Cap. Hour | I13: 5339.8893 | J13: 9.6214221 | K13: 555 | L13: N02:維持顧客作業 | M13: A01:關係維護 | N13: 有附加價值 | O13: 維持成本
A14: 2018 | B14: 3 | C14: 201803 | D14: Kelly Group | E14: 公隆化學股份有限公司 | F14: NASL10:新事業開發部 | G14: NASL11:製程化學課 | H14: A. Cap. Rate*A. Cap. Hour | I14: 8174.3623 | J14: 39.299819 | K14: 208 | L14: N01:取得顧客作業 | M14: A02:市場動態 | N14: 有附加價值 | O14: 取得成本
A15: 2018 | B15: 3 | C15: 201803 | D15: Kelly Group | E15: 公隆化學股份有限公司 | F15: NASL10:新事業開發部 | G15: NASL11:製程化學課 | H15: N. Cap. Rate*A. Cap. Hour | I15: 8174.3623 | J15: 39.299819 | K15: 208 | L15: N01:取得顧客作業 | M15: A02:市場動態 | N15: 有附加價值 | O15: 取得成本
A16: 2018 | B16: 3 | C16: 201803 | D16: Kelly Group | E16: 公隆化學股份有限公司 | F16: NASL10:新事業開發部 | G16: NASL12:電子化學課 | H16: A. Cap. Rate*A. Cap. Hour | I16: 8425.2453 | J16: 9.6014191 | K16: 877.5 | L16: N01:取得顧客作業 | M16: A02:市場動態 | N16: 有附加價值 | O16: 取得成本
A17: 2018 | B17: 3 | C17: 201803 | D17: Kelly Group | E17: 公隆化學股份有限公司 | F17: NASL10:新事業開發部 | G17: NASL12:電子化學課 | H17: N. Cap. Rate*A. Cap. Hour | I17: 8442.7979 | J17: 9.6214221 | K17: 877.5 | L17: N01:取得顧客作業 | M17: A02:市場動態 | N17: 有附加價值 | O17: 取得成本
A18: 2018 | B18: 3 | C18: 201803 | D18: Kelly Group | E18: 公隆化學股份有限公司 | F18: NASL10:新事業開發部 | G18: NASL11:製程化學課 | H18: N. Cap. Rate*A. Cap. Hour | I18: 0 | J18: 39.299819 | K18: 0 | L18: N01:取得顧客作業 | M18: A03:爭取新專案 | N18: 有附加價值 | O18: 取得成本
A19: 2018 | B19: 3 | C19: 201803 | D19: Kelly Group | E19: 公隆化學股份有限公司 | F19: NASL10:新事業開發部 | G19: NASL12:電子化學課 | H19: A. Cap. Rate*A. Cap. Hour | I19: 39101.779 | J19: 9.6014191 | K19: 4072.5 | L19: N01:取得顧客作業 | M19: A03:爭取新專案 | N19: 有附加價值 | O19: 取得成本
A20: 2018 | B20: 3 | C20: 201803 | D20: Kelly Group | E20: 公隆化學股份有限公司 | F20: NASL10:新事業開發部 | G20: NASL12:電子化學課 | H20: N. Cap. Rate*A. Cap. Hour | I20: 39183.242 | J20: 9.6214221 | K20: 4072.5 | L20: N01:取得顧客作業 | M20: A03:爭取新專案 | N20: 有附加價值 | O20: 取得成本
A21: 2018 | B21: 3 | C21: 201803 | D21: Kelly Group | E21: 公隆化學股份有限公司 | F21: NASL10:新事業開發部 | G21: NASL11:製程化學課 | H21: A. Cap. Rate*A. Cap. Hour | I21: 0 | J21: 39.299819 | K21: 0 | L21: N01:取得顧客作業 | M21: A04:專案追蹤 | N21: 有附加價值 | O21: 取得成本
... A134: 2018 | B134: 4 | C134: 201804 | D134: Kelly Group | E134: 公隆化學股份有限公司 | F134: NASL10:新事業開發部 | G134: NASL12:電子化學課 | H134: N. Cap. Rate*A. Cap. Hour | I134: 17149.759 | J134: 12.731818 | K134: 1347 | L134: N02:維持顧客作業 | M134: A01:關係維護 | N134: 有附加價值 | O134: 維持成本
A135: 2018 | B135: 4 | C135: 201804 | D135: Kelly Group | E135: 公隆化學股份有限公司 | F135: NASL10:新事業開發部 | G135: NASL11:製程化學課 | H135: N. Cap. Rate*N. Cap. Hour | I135: 65037.2 | J135: 75.274537 | K135: 864 | L135: N04:其他
A136: 2018 | B136: 4 | C136: 201804 | D136: Kelly Group | E136: 公隆化學股份有限公司 | F136: NASL10:新事業開發部 | G136: NASL12:電子化學課 | H136: N. Cap. Rate*N. Cap. Hour | I136: 36300.96 | J136: 12.731818 | K136: 2851.2 | L136: N04:其他
A137: 2018 | B137: 4 | C137: 201804 | D137: Kelly Group | E137: 公隆化學股份有限公司 | F137: NASL10:新事業開發部 | G137: NASL11:製程化學課 | H137: N. Cap. Rate*N. Cap. Hour | I137: 195111.6 | J137: 75.274537 | K137: 2592 | L137: N03:售後服務作業
A138: 2018 | B138: 4 | C138: 201804 | D138: Kelly Group | E138: 公隆化學股份有限公司 | F138: NASL10:新事業開發部 | G138: NASL12:電子化學課 | H138: N. Cap. Rate*N. Cap. Hour | I138: 32267.52 | J138: 12.731818 | K138: 2534.4 | L138: N03:售後服務作業
A139: 2018 | B139: 4 | C139: 201804 | D139: Kelly Group | E139: 公隆化學股份有限公司 | F139: NASL10:新事業開發部 | G139: NASL11:製程化學課 | H139: N. Cap. Rate*N. Cap. Hour | I139: 130074.4 | J139: 75.274537 | K139: 1728 | L139: N02:維持顧客作業
A140: 2018 | B140: 4 | C140: 201804 | D140: Kelly Group | E140: 公隆化學股份有限公司 | F140: NASL10:新事業開發部 | G140: NASL12:電子化學課 | H140: N. Cap. Rate*N. Cap. Hour | I140: 32267.52 | J140: 12.731818 | K140: 2534.4 | L140: N02:維持顧客作業
A141: 2018 | B141: 4 | C141: 201804 | D141: Kelly Group | E141: 公隆化學股份有限公司 | F141: NASL10:新事業開發部 | G141: NASL11:製程化學課 | H141: N. Cap. Rate*N. Cap. Hour | I141: 260148.8 | J141: 75.274537 | K141: 3456 | L141: N01:取得顧客作業
A142: 2018 | B142: 4 | C142: 201804 | D142: Kelly Group | E142: 公隆化學股份有限公司 | F142: NASL10:新事業開發部 | G142: NASL12:電子化學課 | H142: N. Cap. Rate*N. Cap. Hour | I142: 100836 | J142: 12.731818 | K142: 7920 | L142: N01:取得顧客作業
A143: 2018 | B143: 5 | C143: 201805 | D143: Kelly Group | E143: 公隆化學股份有限公司 | F143: NASL10:新事業開發部 | G143: NASL11:製程化學課 | H143: N. Cap. Rate*N. Cap. Hour | I143: 209932 | J143: 49.699811 | K143: 4224 | L143: N01:取得顧客作業
A144: 2018 | B144: 5 | C144: 201805 | D144: Kelly Group | E144: 公隆化學股份有限公司 | F144: NASL10:新事業開發部 | G144: NASL12:電子化學課 | H144: N. Cap. Rate*N. Cap. Hour | I144: 81403.5 | J144: 8.2727134 | K144: 9840 | L144: N01:取得顧客作業
A145: 2018 | B145: 5 | C145: 201805 | D145: Kelly Group | E145: 公隆化學股份有限公司 | F145: NASL10:新事業開發部 | G145: NASL11:製程化學課 | H145: N. Cap. Rate*N. Cap. Hour | I145: 104966 | J145: 49.699811 | K145: 2112 | L145: N02:維持顧客作業
A146: 2018 | B146: 5 | C146: 201805 | D146: Kelly Group | E146: 公隆化學股份有限公司 | F146: NASL10:新事業開發部 | G146: NASL12:電子化學課 | H146: N. Cap. Rate*N. Cap. Hour | I146: 26049.12 | J146: 8.2727134 | K146: 3148.8 | L146: N02:維持顧客作業
... A150: 2018 | B150: 5 | C150: 201805 | D150: Kelly Group | E150: 公隆化學股份有限公司 | F150: NASL10:新事業開發部 | G150: NASL12:電子化學課 | H150: N. Cap. Rate*N. Cap. Hour | I150: 29305.26 | J150: 8.2727134 | K150: 3542.4 | L150: N04:其他
A151: 2018 | B151: 5 | C151: 201805 | D151: Kelly Group | E151: 公隆化學股份有限公司 | F151: NASL10:新事業開發部 | G151: NASL11:製程化學課 | H151: A. Cap. Rate*A. Cap. Hour | I151: 38964.652 | J151: 49.699811 | K151: 784 | L151: N02:維持顧客作業 | M151: A01:關係維護 | N151: 有附加價值 | O151: 維持成本
A152: 2018 | B152: 5 | C152: 201805 | D152: Kelly Group | E152: 公隆化學股份有限公司 | F152: NASL10:新事業開發部 | G152: NASL11:製程化學課 | H152: N. Cap. Rate*A. Cap. Hour | I152: 38964.652 | J152: 49.699811 | K152: 784 | L152: N02:維持顧客作業 | M152: A01:關係維護 | N152: 有附加價值 | O152: 維持成本
A153: 2018 | B153: 5 | C153: 201805 | D153: Kelly Group | E153: 公隆化學股份有限公司 | F153: NASL10:新事業開發部 | G153: NASL12:電子化學課 | H153: N. Cap. Rate*A. Cap. Hour | I153: 0 | J153: 8.2727134 | K153: 0 | L153: N02:維持顧客作業 | M153: A01:關係維護 | N153: 有附加價值 | O153: 維持成本
A154: 2018 | B154: 5 | C154: 201805 | D154: Kelly Group | E154: 公隆化學股份有限公司 | F154: NASL10:新事業開發部 | G154: NASL11:製程化學課 | H154: N. Cap. Rate*A. Cap. Hour | I154: 0 | J154: 49.699811 | K154: 0 | L154: N01:取得顧客作業 | M154: A02:市場動態 | N154: 有附加價值 | O154: 取得成本
A155: 2018 | B155: 5 | C155: 201805 | D155: Kelly Group | E155: 公隆化學股份有限公司 | F155: NASL10:新事業開發部 | G155: NASL12:電子化學課 | H155: A. Cap. Rate*A. Cap. Hour | I155: 3970.9024 | J155: 8.2727134 | K155: 480 | L155: N01:取得顧客作業 | M155: A02:市場動態 | N155: 有附加價值 | O155: 取得成本
A156: 2018 | B156: 5 | C156: 201805 | D156: Kelly Group | E156: 公隆化學股份有限公司 | F156: NASL10:新事業開發部 | G156: NASL12:電子化學課 | H156: N. Cap. Rate*A. Cap. Hour | I156: 3970.9024 | J156: 8.2727134 | K156: 480 | L156: N01:取得顧客作業 | M156: A02:市場動態 | N156: 有附加價值 | O156: 取得成本
A157: 2018 | B157: 5 | C157: 201805 | D157: Kelly Group | E157: 公隆化學股份有限公司 | F157: NASL10:新事業開發部 | G157: NASL11:製程化學課 | H157: N. Cap. Rate*A. Cap. Hour | I157: 0 | J157: 49.699811 | K157: 0 | L157: N01:取得顧客作業 | M157: A03:爭取新專案 | N157: 有附加價值 | O157: 取得成本
A158: 2018 | B158: 5 | C158: 201805 | D158: Kelly Group | E158: 公隆化學股份有限公司 | F158: NASL10:新事業開發部 | G158: NASL12:電子化學課 | H158: A. Cap. Rate*A. Cap. Hour | I158: 32106.401 | J158: 8.2727134 | K158: 3881 | L158: N01:取得顧客作業 | M158: A03:爭取新專案 | N158: 有附加價值 | O158: 取得成本
A159: 2018 | B159: 5 | C159: 201805 | D159: Kelly Group | E159: 公隆化學股份有限公司 | F159: NASL10:新事業開發部 | G159: NASL12:電子化學課 | H159: N. Cap. Rate*A. Cap. Hour | I159: 32106.401 | J159: 8.2727134 | K159: 3881 | L159: N01:取得顧客作業 | M159: A03:爭取新專案 | N159: 有附加價值 | O159: 取得成本
A160: 2018 | B160: 5 | C160: 201805 | D160: Kelly Group | E160: 公隆化學股份有限公司 | F160: NASL10:新事業開發部 | G160: NASL11:製程化學課 | H160: N. Cap. Rate*A. Cap. Hour | I160: 0 | J160: 49.699811 | K160: 0 | L160: N01:取得顧客作業 | M160: A04:專案追蹤 | N160: 有附加價值 | O160: 取得成本
A161: 2018 | B161: 5 | C161: 201805 | D161: Kelly Group | E161: 公隆化學股份有限公司 | F161: NASL10:新事業開發部 | G161: NASL12:電子化學課 | H161: A. Cap. Rate*A. Cap. Hour | I161: 26472.683 | J161: 8.2727134 | K161: 3200 | L161: N01:取得顧客作業 | M161: A04:專案追蹤 | N161: 有附加價值 | O161: 取得成本
A162: 2018 | B162: 5 | C162: 201805 | D162: Kelly Group | E162: 公隆化學股份有限公司 | F162: NASL10:新事業開發部 | G162: NASL12:電子化學課 | H162: N. Cap. Rate*A. Cap. Hour | I162: 26472.683 | J162: 8.2727134 | K162: 3200 | L162: N01:取得顧客作業 | M162: A04:專案追蹤 | N162: 有附加價值 | O162: 取得成本
... A209: 2018 | B209: 5 | C209: 201805 | D209: Kelly Group | E209: 公隆化學股份有限公司 | F209: NASL10:新事業開發部 | G209: NASL12:電子化學課 | H209: N. Cap. Rate*A. Cap. Hour | I209: 0 | J209: 8.2727134 | K209: 0 | L209: N03:售後服務作業 | M209: A22:帳款收回 | N209: 有附加價值 | O209: 服務成本

Sheet 單位實際作業成本
A2: 成本類型 | B2: A. Cap. Rate*A. Cap. Hour
A4: 加總 - 作業中心動因費率 | B4: 欄標籤
A5: 列標籤 | B5: 3 | C5: 4 | D5: 5 | E5: 總計
A6: NASL11:製程化學課 | B6: 314.39855 | C6: 526.92176 | D6: 447.2983 | E6: 1288.6186 | G6: 3月 | H6: 4月 | I6: 5月
A7: A01:關係維護 | B7: 39.299819 | D7: 49.699811 | E7: 88.999629 | G7: 8種作業 | H7: 7種作業 | I7: 9種作業
A8: A02:市場動態 | B8: 39.299819 | E8: 39.299819 | G8: 市場動態專案追蹤
A9: A04:專案追蹤 | B9: 39.299819 | E9: 39.299819
A10: A05:拜訪新客戶 | B10: 39.299819 | C10: 75.274537 | D10: 49.699811 | E10: 164.27417
A11: A06:小批量試產 | D11: 49.699811 | E11: 49.699811
A12: A07:推薦新產品 | B12: 39.299819 | E12: 39.299819
A13: A08:新線(產品)追蹤 | D13: 49.699811 | E13: 49.699811
A14: A09:偕同技術服務 | B14: 39.299819 | C14: 75.274537 | D14: 49.699811 | E14: 164.27417
A15: A11:取樣分析 | B15: 39.299819 | C15: 75.274537 | D15: 49.699811 | E15: 164.27417
A16: A16:試樣 | D16: 49.699811 | E16: 49.699811
A17: A17:製程改善 | D17: 49.699811 | E17: 49.699811
A18: A18:Kelly內部事項 | B18: 39.299819 | C18: 75.274537 | D18: 49.699811 | E18: 164.27417
A19: A19:目標客戶拜訪 | C19: 75.274537 | E19: 75.274537
A20: A20:合作夥伴拜訪 | C20: 75.274537 | E20: 75.274537
A21: A22:帳款收回 | C21: 75.274537 | E21: 75.274537
A22: NASL12:電子化學課 | B22: 115.21703 | C22: 127.31818 | D22: 49.63628 | E22: 292.17149
A23: A01:關係維護 | B23: 9.6014191 | C23: 12.731818 | E23: 22.333237
A24: A02:市場動態 | B24: 9.6014191 | C24: 12.731818 | D24: 8.2727134 | E24: 30.605951
A25: A03:爭取新專案 | B25: 9.6014191 | C25: 12.731818 | D25: 8.2727134 | E25: 30.605951
A26: A04:專案追蹤 | B26: 9.6014191 | C26: 12.731818 | D26: 8.2727134 | E26: 30.605951
A27: A05:拜訪新客戶 | B27: 9.6014191 | C27: 12.731818 | D27: 8.2727134 | E27: 30.605951
A28: A07:推薦新產品 | B28: 9.6014191 | C28: 12.731818 | E28: 22.333237
A29: A08:新線(產品)追蹤 | B29: 9.6014191 | E29: 9.6014191
A30: A09:偕同技術服務 | B30: 9.6014191 | E30: 9.6014191
A31: A10:偕同原廠拜訪 | B31: 9.6014191 | E31: 9.6014191
A32: A11:取樣分析 | B32: 9.6014191 | E32: 9.6014191
A33: A12:客服諮詢 | B33: 9.6014191 | E33: 9.6014191
A34: A13:客訴處理 | C34: 12.731818 | E34: 12.731818
A35: A18:Kelly內部事項 | B35: 9.6014191 | C35: 12.731818 | D35: 8.2727134 | E35: 30.605951
A36: A19:目標客戶拜訪 | C36: 12.731818 | D36: 8.2727134 | E36: 21.004532
A37: A22:帳款收回 | C37: 12.731818 | E37: 12.731818
A38: 總計 | B38: 429.61558 | C38: 654.23994 | D38: 496.93458 | E38: 1580.7901

Sheet 附加價值
A2: 成本類型 | B2: A. Cap. Rate*A. Cap. Hour
A4: 加總 - 金額 | B4: Column Labels
A5: Row Labels | B5: 3 | C5: 4 | D5: 5 | E5: Grand Total
A6: 有附加價值 | B6: 646311 | C6: 848377.24 | D6: 687637 | E6: 2182325.2
A7: 無附加價值 | C7: 3666.7636 | E7: 3666.7636
A8: A13:客訴處理 | C8: 3666.7636 | E8: 3666.7636
A9: Grand Total | B9: 646311 | C9: 852044 | D9: 687637 | E9: 2185992

Sheet 顧客服務屬性
A1: 成本類型 | B1: A. Cap. Rate*A. Cap. Hour
A3: 加總 - 金額 | B3: Column Labels
A4: Row Labels | B4: 3 | C4: 4 | D4: 5 | E4: Grand Total
A5: NA | B5: 309323.22 | C5: 469410.75 | D5: 389544.87 | E5: 1168278.8
A6: 取得成本 | B6: 301468.58 | C6: 361014.62 | D6: 253262.9 | E6: 915746.1
A7: 服務成本 | B7: 5885.6699 | C7: 4468.8682 | D7: 5864.5777 | E7: 16219.116
A8: A08:新線(產品)追蹤 | B8: 1276.9887 | D8: 2882.589 | E8: 4159.5778
A9: A12:客服諮詢 | B9: 4608.6812 | E9: 4608.6812
A10: A13:客訴處理 | C10: 3666.7636 | E10: 3666.7636
A11: A17:製程改善 | D11: 2981.9886 | E11: 2981.9886
A12: A22:帳款收回 | C12: 802.10455 | E12: 802.10455
A13: 維持成本 | B13: 29633.534 | C13: 17149.759 | D13: 38964.652 | E13: 85747.945
A14: Grand Total | B14: 646311 | C14: 852044 | D14: 687637 | E14: 2185992

Sheet ActivityCenter
A1: 年 | B1: 月份 | C1: 期間資料版本 | D1: 公司 | E1: 事業單位 | F1: 作業中心 | G1: 作業中心-第一階 | H1: 作業中心-第二階 | I1: 人/機時 | J1: 作業-第一階 | K1: 正常產能費率 | L1: 實際產能費率 | M1: 正常產能(時間) | N1: 實際產能(時間) | O1: 正常產能金額(N*N) | P1: 實際產能金額(A*A) | Q1: 剩餘(超用)產能時間
A2: 2018 | B2: 3 | C2: 201803 | D2: Kelly Group | E2: 公隆化學股份有限公司 | F2: NASL11:製程化學課 | G2: NASL10:新事業開發部 | H2: NASL11:製程化學課 | I2: MAN POWER | J2: N04:其他 | K2: 39.299819 | L2: 39.299819 | M2: 1104 | N2: 5760 | O2: 43387 | P2: 226366.96 | Q2: -4656
A3: 2018 | B3: 3 | C3: 201803 | D3: Kelly Group | E3: 公隆化學股份有限公司 | F3: NASL11:製程化學課 | G3: NASL10:新事業開發部 | H3: NASL11:製程化學課 | I3: MAN POWER | J3: N03:售後服務作業 | K3: 39.299819 | L3: 39.299819 | M3: 3312 | N3: 0 | O3: 130161 | P3: 0 | Q3: 3312
A4: 2018 | B4: 3 | C4: 201803 | D4: Kelly Group | E4: 公隆化學股份有限公司 | F4: NASL11:製程化學課 | G4: NASL10:新事業開發部 | H4: NASL11:製程化學課 | I4: MAN POWER | J4: N01:取得顧客作業 | K4: 39.299819 | L4: 39.299819 | M4: 4416 | N4: 5072 | O4: 173548 | P4: 199328.68 | Q4: -656
A5: 2018 | B5: 3 | C5: 201803 | D5: Kelly Group | E5: 公隆化學股份有限公司 | F5: NASL11:製程化學課 | G5: NASL10:新事業開發部 | H5: NASL11:製程化學課 | I5: MAN POWER | J5: N02:維持顧客作業 | K5: 39.299819 | L5: 39.299819 | M5: 2208 | N5: 208 | O5: 86774 | P5: 8174.3623 | Q5: 2000
A6: 2018 | B6: 3 | C6: 201803 | D6: Kelly Group | E6: 公隆化學股份有限公司 | F6: NASL12:電子化學課 | G6: NASL10:新事業開發部 | H6: NASL12:電子化學課 | I6: MAN POWER | J6: N02:維持顧客作業 | K6: 9.6214221 | L6: 9.6014191 | M6: 3532.8 | N6: 2235 | O6: 33990.56 | P6: 21459.172 | Q6: 1297.8
A7: 2018 | B7: 3 | C7: 201803 | D7: Kelly Group | E7: 公隆化學股份有限公司 | F7: NASL12:電子化學課 | G7: NASL10:新事業開發部 | H7: NASL12:電子化學課 | I7: MAN POWER | J7: N04:其他 | K7: 9.6214221 | L7: 9.6014191 | M7: 3974.4 | N7: 8640 | O7: 38239.38 | P7: 82956.261 | Q7: -4665.6
A8: 2018 | B8: 3 | C8: 201803 | D8: Kelly Group | E8: 公隆化學股份有限公司 | F8: NASL12:電子化學課 | G8: NASL10:新事業開發部 | H8: NASL12:電子化學課 | I8: MAN POWER | J8: N01:取得顧客作業 | K8: 9.6214221 | L8: 9.6014191 | M8: 11040 | N8: 10638 | O8: 106220.5 | P8: 102139.9 | Q8: 402
A9: 2018 | B9: 3 | C9: 201803 | D9: Kelly Group | E9: 公隆化學股份有限公司 | F9: NASL12:電子化學課 | G9: NASL10:新事業開發部 | H9: NASL12:電子化學課 | I9: MAN POWER | J9: N03:售後服務作業 | K9: 9.6214221 | L9: 9.6014191 | M9: 3532.8 | N9: 613 | O9: 33990.56 | P9: 5885.6699 | Q9: 2919.8
A10: 2018 | B10: 4 | C10: 201804 | D10: Kelly Group | E10: 公隆化學股份有限公司 | F10: NASL11:製程化學課 | G10: NASL10:新事業開發部 | H10: NASL11:製程化學課 | I10: MAN POWER | J10: N04:其他 | K10: 75.274537 | L10: 75.274537 | M10: 864 | N10: 4937 | O10: 65037.2 | P10: 371630.39 | Q10: -4073
A11: 2018 | B11: 4 | C11: 201804 | D11: Kelly Group | E11: 公隆化學股份有限公司 | F11: NASL11:製程化學課 | G11: NASL10:新事業開發部 | H11: NASL11:製程化學課 | I11: MAN POWER | J11: N03:售後服務作業 | K11: 75.274537 | L11: 75.274537 | M11: 2592 | N11: 0 | O11: 195111.6 | P11: 0 | Q11: 2592
A12: 2018 | B12: 4 | C12: 201804 | D12: Kelly Group | E12: 公隆化學股份有限公司 | F12: NASL11:製程化學課 | G12: NASL10:新事業開發部 | H12: NASL11:製程化學課 | I12: MAN POWER | J12: N02:維持顧客作業 | K12: 75.274537 | L12: 75.274537 | M12: 1728 | N12: 0 | O12: 130074.4 | P12: 0 | Q12: 1728
A13: 2018 | B13: 4 | C13: 201804 | D13: Kelly Group | E13: 公隆化學股份有限公司 | F13: NASL11:製程化學課 | G13: NASL10:新事業開發部 | H13: NASL11:製程化學課 | I13: MAN POWER | J13: N01:取得顧客作業 | K13: 75.274537 | L13: 75.274537 | M13: 3456 | N13: 3703 | O13: 260148.8 | P13: 278741.61 | Q13: -247
... A25: 2018 | B25: 5 | C25: 201805 | D25: Kelly Group | E25: 公隆化學股份有限公司 | F25: NASL12:電子化學課 | G25: NASL10:新事業開發部 | H25: NASL12:電子化學課 | I25: MAN POWER | J25: N04:其他 | K25: 8.2727134 | L25: 8.2727134 | M25: 3542.4 | N25: 9600 | O25: 29305.26 | P25: 79418.049 | Q25: -6057.6

Sheet 超用剩餘
B3: 欄標籤
B4: 3 | E4: 4 | H4: 5 | K4: 加總 - 正常產能(時間) 的加總 | L4: 加總 - 實際產能(時間) 的加總 | M4: 加總 - 剩餘(超用)產能時間 的加總
A5: 列標籤 | B5: 加總 - 正常產能(時間) | C5: 加總 - 實際產能(時間) | D5: 加總 - 剩餘(超用)產能時間 | E5: 加總 - 正常產能(時間) | F5: 加總 - 實際產能(時間) | G5: 加總 - 剩餘(超用)產能時間 | H5: 加總 - 正常產能(時間) | I5: 加總 - 實際產能(時間) | J5: 加總 - 剩餘(超用)產能時間
A6: NASL11:製程化學課 | B6: 11040 | C6: 11040 | D6: 0 | E6: 8640 | F6: 8640 | G6: 0 | H6: 10560 | I6: 10560 | J6: 0 | K6: 30240 | L6: 30240 | M6: 0
A7: NASL12:電子化學課 | B7: 22080 | C7: 22126 | D7: -46 | E7: 15840 | F7: 15840 | G7: 0 | H7: 19680 | I7: 19680 | J7: 0 | K7: 57600 | L7: 57646 | M7: -46
A8: 總計 | B8: 33120 | C8: 33166 | D8: -46 | E8: 24480 | F8: 24480 | G8: 0 | H8: 30240 | I8: 30240 | J8: 0 | K8: 87840 | L8: 87886 | M8: -46

Sheet ActivityDriver
A1: 年 | B1: 月份 | C1: 期間資料版本 | D1: 公司 | E1: 事業單位 | F1: 作業中心 | G1: 實際產能費率成本 | H1: 正常產能費率成本 | I1: 作業-第一階 | J1: 作業-第二階 | K1: 作業動因 | L1: 作業動因值 | M1: 價值標的類型 | N1: 價值標的
A2: 2018 | B2: 3 | C2: 201803 | D2: Kelly Group | E2: 公隆化學股份有限公司 | F2: NASL12:電子化學課 | G2: 4608.6812 | H2: 4618.2826 | I2: N01:取得顧客作業 | J2: A03:爭取新專案 | K2: 拜訪時間 | L2: 480 | M2: CustomerProject:顧客專案 | N2: CPCRM12107:專案-達興
A3: 2018 | B3: 3 | C3: 201803 | D3: Kelly Group | E3: 公隆化學股份有限公司 | F3: NASL12:電子化學課 | G3: 1843.4725 | H3: 1847.313 | I3: N01:取得顧客作業 | J3: A03:爭取新專案 | K3: 拜訪時間 | L3: 192 | M3: CustomerProject:顧客專案 | N3: CPCRM19560:專案-山鶯欣興電子
A4: 2018 | B4: 3 | C4: 201803 | D4: Kelly Group | E4: 公隆化學股份有限公司 | F4: NASL12:電子化學課 | G4: 2064.3051 | H4: 2068.6058 | I4: N01:取得顧客作業 | J4: A03:爭取新專案 | K4: 拜訪時間 | L4: 215 | M4: CustomerProject:顧客專案 | N4: CPCRM19560:專案-山鶯欣興電子
A5: 2018 | B5: 3 | C5: 201803 | D5: Kelly Group | E5: 公隆化學股份有限公司 | F5: NASL12:電子化學課 | G5: 2736.4045 | H5: 2742.1053 | I5: N01:取得顧客作業 | J5: A03:爭取新專案 | K5: 拜訪時間 | L5: 285 | M5: CustomerProject:顧客專案 | N5: CPCRM20039:專案-樹林台電研究所
A6: 2018 | B6: 3 | C6: 201803 | D6: Kelly Group | E6: 公隆化學股份有限公司 | F6: NASL12:電子化學課 | G6: 4464.6599 | H6: 4473.9613 | I6: N01:取得顧客作業 | J6: A03:爭取新專案 | K6: 拜訪時間 | L6: 465 | M6: CustomerProject:顧客專案 | N6: CPCRM20254:專案-台灣奈晶
A7: 2018 | B7: 3 | C7: 201803 | D7: Kelly Group | E7: 公隆化學股份有限公司 | F7: NASL12:電子化學課 | G7: 3072.4541 | H7: 3078.8551 | I7: N01:取得顧客作業 | J7: A03:爭取新專案 | K7: 拜訪時間 | L7: 320 | M7: CustomerProject:顧客專案 | N7: CPCRM08397:專案-奇美實業
A8: 2018 | B8: 3 | C8: 201803 | D8: Kelly Group | E8: 公隆化學股份有限公司 | F8: NASL12:電子化學課 | G8: 2304.3406 | H8: 2309.1413 | I8: N01:取得顧客作業 | J8: A03:爭取新專案 | K8: 拜訪時間 | L8: 240 | M8: CustomerProject:顧客專案 | N8: CPCRM11452:專案-佳邦
A9: 2018 | B9: 3 | C9: 201803 | D9: Kelly Group | E9: 公隆化學股份有限公司 | F9: NASL12:電子化學課 | G9: 1315.3944 | H9: 1318.1348 | I9: N01:取得顧客作業 | J9: A03:爭取新專案 | K9: 拜訪時間 | L9: 137 | M9: CustomerProject:顧客專案 | N9: CPCRM17041:專案-新竹-錸德
A10: 2018 | B10: 3 | C10: 201803 | D10: Kelly Group | E10: 公隆化學股份有限公司 | F10: NASL12:電子化學課 | G10: 772.91424 | H10: 774.52448 | I10: N01:取得顧客作業 | J10: A03:爭取新專案 | K10: 拜訪時間 | L10: 80.5 | M10: CustomerProject:顧客專案 | N10: CPCRM17041:專案-新竹-錸德
A11: 2018 | B11: 3 | C11: 201803 | D11: Kelly Group | E11: 公隆化學股份有限公司 | F11: NASL12:電子化學課 | G11: 921.73624 | H11: 923.65652 | I11: N01:取得顧客作業 | J11: A03:爭取新專案 | K11: 拜訪時間 | L11: 96 | M11: CustomerProject:顧客專案 | N11: CP永光二廠:專案-永光二廠
A12: 2018 | B12: 3 | C12: 201803 | D12: Kelly Group | E12: 公隆化學股份有限公司 | F12: NASL12:電子化學課 | G12: 1843.4725 | H12: 1847.313 | I12: N01:取得顧客作業 | J12: A03:爭取新專案 | K12: 拜訪時間 | L12: 192 | M12: CustomerProject:顧客專案 | N12: CPCRM05175:專案-永光三廠
A13: 2018 | B13: 3 | C13: 201803 | D13: Kelly Group | E13: 公隆化學股份有限公司 | F13: NASL12:電子化學課 | G13: 1536.2271 | H13: 1539.4275 | I13: N01:取得顧客作業 | J13: A03:爭取新專案 | K13: 拜訪時間 | L13: 160 | M13: CustomerProject:顧客專案 | N13: CPCRM08460:專案-台虹科技
... A244: 2018 | B244: 5 | C244: 201805 | D244: Kelly Group | E244: 公隆化學股份有限公司 | F244: NASL11:製程化學課 | G244: 23855.909 | H244: 23855.909 | I244: N01:取得顧客作業 | J244: A16:試樣 | K244: 拜訪時間 | L244: 480 | M244: CustomerProject:顧客專案 | N244: CPCRM01101:專案-興展企業

Sheet 專案作業時間
A3: 加總 - 作業動因值 | B3: 欄標籤
A4: 列標籤 | B4: 3 | C4: 4 | D4: 5 | E4: 總計
A5: NASL11:製程化學課 | B5: 11040 | C5: 8640 | D5: 10560 | E5: 30240
A6: CP other cus:專案-other customer | B6: 5760 | C6: 4800 | D6: 6240 | E6: 16800
A7: CPCRM00550:專案-瑞興發 | B7: 48 | D7: 58 | E7: 106
A8: CPCRM00783:專案-亞洲漢威 | B8: 58 | E8: 58
A9: CPCRM00937:專案-大勤化成 | B9: 480 | E9: 480
A10: CPCRM01037:專案-華邦電 | B10: 226 | C10: 15 | E10: 241
A11: CPCRM01042:專案-欣銓科技 | B11: 136 | D11: 161 | E11: 297
A12: CPCRM01046:專案-華泰電子 | C12: 55 | D12: 146 | E12: 201
A13: CPCRM01049:專案-台星科 | B13: 145 | E13: 145
A14: CPCRM01052:專案-福懋科技 | B14: 137 | D14: 480 | E14: 617
A15: CPCRM01053:專案-渼豐表面處理 | C15: 101 | E15: 101
A16: CPCRM01073:專案-榮聰精密 | D16: 60 | E16: 60
A17: CPCRM01090:專案-台弟工業 | B17: 67 | E17: 67
A18: CPCRM01091:專案-群浤科技 | B18: 231 | E18: 231
A19: CPCRM01093:專案-巨品表面 | B19: 64 | E19: 64
A20: CPCRM01094:專案-旭德科技 | B20: 438 | C20: 265 | E20: 703
A21: CPCRM01095:專案-崇越石英製造廠 | B21: 215 | C21: 111 | E21: 326
A22: CPCRM01096:專案-南豐工業 | B22: 139 | E22: 139
A23: CPCRM01097:專案-矽格 | B23: 452 | E23: 452
A24: CPCRM01101:專案-興展企業 | B24: 123 | C24: 136 | D24: 908 | E24: 1167
A25: CPCRM01102:專案-欣旻工業 | B25: 131 | E25: 131
A26: CPCRM01103:專案-璟德電子 | B26: 135 | E26: 135
A27: CPCRM01105:專案-萬能科大 | B27: 416 | E27: 416
A28: CPCRM01109:專案-伍德邁 | D28: 367 | E28: 367
A29: CPCRM01111:專案-辛耘企業-二廠 | B29: 126 | D29: 79 | E29: 205
A30: CPCRM01117:專案-正修科大 | B30: 245 | E30: 245
A31: CPCRM01118:專案-捷暘 | B31: 480 | E31: 480
A32: CPCRM01121:專案-大發金屬 | C32: 171 | D32: 69 | E32: 240
A33: CPCRM01122:專案-玉美-生物科技 | C33: 155 | E33: 155
A34: CPCRM01123:專案-洗旺國際 | C34: 82 | E34: 82
A35: CPCRM01124:專案-日月展金屬 | C35: 72 | E35: 72
A36: CPCRM01125:專案-昌旺汽材 | C36: 98 | D36: 114 | E36: 212
A37: CPCRM01126:專案-彰陽工業 | C37: 70 | E37: 70
A38: CPCRM01127:專案-杰昌金屬 | C38: 157 | E38: 157
A39: CPCRM01128:專案-哈伯精密 | C39: 100 | E39: 100
A40: CPCRM01129:專案-雷電光能 | C40: 416 | D40: 316 | E40: 732
A41: CPCRM01130:專案-普聯國際 | C41: 137 | D41: 472 | E41: 609
A42: CPCRM01132:專案-台灣京濱化 | C42: 155 | E42: 155
A43: CPCRM01133:專案-盛復工業-大肚廠 | C43: 55 | E43: 55
A44: CPCRM01140:專案-朝宇航太科技二廠 | C44: 166 | D44: 155 | E44: 321
A45: CPCRM01146:專案-善存科技 | D45: 480 | E45: 480
A46: CPCRM01149:專案-福特六和 | D46: 82 | E46: 82
A47: CPCRM1106:專案-台灣積水原聚 | B47: 144 | C47: 104 | E47: 248
A48: CPCRM1107:專案-長春人造樹脂 | B48: 102 | E48: 102
A49: CPCRM14295:專案-kelly實驗室 | B49: 480 | E49: 480
A50: CPCRM17319:專案-高雄李長榮化工 | C50: 140 | D50: 104 | E50: 244
A51: CPCRM20308:專案-九怡工業 | C51: 480 | E51: 480
A52: CP世豐螺絲:專案-世豐螺絲 | C52: 119 | D52: 17 | E52: 136
A53: CP恆耀工業:專案-恆耀工業 | B53: 62 | E53: 62
A54: CP華震科技:專案-華震科技 | C54: 480 | D54: 252 | E54: 732
A55: NASL12:電子化學課 | B55: 22126 | C55: 15840 | D55: 19680 | E55: 57646
A56: 總計 | B56: 33166 | C56: 24480 | D56: 30240 | E56: 87886

Sheet PartStock
A1: 年 | B1: 月份 | C1: 期間資料版本 | D1: 公司 | E1: 事業單位 | F1: 價值標的類型 | G1: 料號 | H1: 類型 | I1: 數量 | J1: 金額
A2: 2018 | B2: 3 | C2: 201803 | D2: Kelly Group | E2: 公隆化學股份有限公司 | F2: 原物料 | G2: 61000017 | H2: 進料入庫 | I2: 300 | J2: 25265
A3: 2018 | B3: 3 | C3: 201803 | D3: Kelly Group | E3: 公隆化學股份有限公司 | F3: 原物料 | G3: 61000027 | H3: 進料入庫 | I3: 150 | J3: 5830
A4: 2018 | B4: 3 | C4: 201803 | D4: Kelly Group | E4: 公隆化學股份有限公司 | F4: 原物料 | G4: 61000028 | H4: 進料入庫 | I4: 480 | J4: 15966
A5: 2018 | B5: 3 | C5: 201803 | D5: Kelly Group | E5: 公隆化學股份有限公司 | F5: 原物料 | G5: 71000576 | H5: 進料入庫 | I5: 20 | J5: 2637
A6: 2018 | B6: 3 | C6: 201803 | D6: Kelly Group | E6: 公隆化學股份有限公司 | F6: 原物料 | G6: 74000063 | H6: 進料入庫 | I6: 20 | J6: 4592
A7: 2018 | B7: 3 | C7: 201803 | D7: Kelly Group | E7: 公隆化學股份有限公司 | F7: 原物料 | G7: 74000071 | H7: 進料入庫 | I7: 60 | J7: 7262
A8: 2018 | B8: 3 | C8: 201803 | D8: Kelly Group | E8: 公隆化學股份有限公司 | F8: 原物料 | G8: 74000158 | H8: 進料入庫 | I8: 428 | J8: 44091
A9: 2018 | B9: 3 | C9: 201803 | D9: Kelly Group | E9: 公隆化學股份有限公司 | F9: 原物料 | G9: 74000162 | H9: 進料入庫 | I9: 1000 | J9: 71469
A10: 2018 | B10: 3 | C10: 201803 | D10: Kelly Group | E10: 公隆化學股份有限公司 | F10: 原物料 | G10: 74000193 | H10: 進料入庫 | I10: 415.6 | J10: 33664
A11: 2018 | B11: 3 | C11: 201803 | D11: Kelly Group | E11: 公隆化學股份有限公司 | F11: 原物料 | G11: 74000242 | H11: 進料入庫 | I11: 36 | J11: 13292
A12: 2018 | B12: 3 | C12: 201803 | D12: Kelly Group | E12: 公隆化學股份有限公司 | F12: 原物料 | G12: 74000245 | H12: 進料入庫 | I12: 1250 | J12: 190000
A13: 2018 | B13: 3 | C13: 201803 | D13: Kelly Group | E13: 公隆化學股份有限公司 | F13: 原物料 | G13: 74000252 | H13: 進料入庫 | I13: 90 | J13: 27815
... A159: 2018 | B159: 5 | C159: 201805 | D159: Kelly Group | E159: 公隆化學股份有限公司 | F159: 產品 | G159: 88100060 | H159: 訂單出貨 | I159: -5 | J159: -60449

Sheet 存貨
A3: 加總 - 數量 | B3: 欄標籤
A4: 列標籤 | B4: 訂單出貨 | C4: 進料入庫 | D4: 總計
A5: 61000017 | B5: -1720 | C5: 1720 | D5: 0
A6: 61000027 | B6: -960 | C6: 960 | D6: 0
A7: 61000028 | B7: -960 | C7: 960 | D7: 0
A8: 71000576 | B8: -60 | C8: 60 | D8: 0
A9: 72000019 | B9: -80 | C9: 80 | D9: 0
A10: 72000045 | B10: -19.7 | C10: 19.7 | D10: 0
A11: 72100012 | B11: -160 | C11: 160 | D11: 0
A12: 72100014 | B12: -280 | C12: 280 | D12: 0
A13: 74000063 | B13: -20 | C13: 20 | D13: 0
A14: 74000071 | B14: -80 | C14: 80 | D14: 0
A15: 74000150 | B15: -40 | C15: 40 | D15: 0
A16: 74000158 | B16: -722 | C16: 722 | D16: 0
... A51: 總計 | B51: -18037.9 | C51: 18037.9 | D51: 0

Sheet Project
A1: 年 | B1: 月份 | C1: 期間資料版本 | D1: 公司 | E1: 事業單位 | F1: 專案代碼 | G1: 專案名稱 | H1: 價值標的類型 | I1: 類型 | J1: 作業中心 | K1: 資源/作業 | L1: 代碼 | M1: 金額 | N1: 實際產能(分鐘) | O1: 產品 | P1: 數量 | Q1: 業務工程師
A2: 2018 | B2: 3 | C2: 201803 | D2: Kelly Group | E2: 公隆化學股份有限公司 | F2: CPunknow | G2: 專案-未分析顧客 | H2: CustomerProject | I2: 成本累積 | J2: NASL10:新事業開發部 | K2: Resource | L2: R05:其他費用 | M2: 3092
A3: 2018 | B3: 3 | C3: 201803 | D3: Kelly Group | E3: 公隆化學股份有限公司 | F3: CPCRM00696 | G3: 專案-健達生物 | H3: CustomerProject | I3: 成本累積 | J3: NASL11:製程化學課 | K3: Resource | L3: R03:交際費用 | M3: 300 | Q3: Vincent
A4: 2018 | B4: 3 | C4: 201803 | D4: Kelly Group | E4: 公隆化學股份有限公司 | F4: CPCRM00696 | G4: 專案-健達生物 | H4: CustomerProject | I4: 成本累積 | J4: NASL11:製程化學課 | K4: Resource | L4: R04:樣品費 | M4: 6350 | Q4: Vincent
A5: 2018 | B5: 3 | C5: 201803 | D5: Kelly Group | E5: 公隆化學股份有限公司 | F5: CPCRM00911 | G5: 專案-台灣鉅邁 | H5: CustomerProject | I5: 成本累積 | J5: NASL11:製程化學課 | K5: Resource | L5: R04:樣品費 | M5: 3372 | Q5: Vincent
A6: 2018 | B6: 3 | C6: 201803 | D6: Kelly Group | E6: 公隆化學股份有限公司 | F6: CPunknow | G6: 專案-未分析顧客 | H6: CustomerProject | I6: 成本累積 | J6: NASL11:製程化學課 | K6: Resource | L6: R05:其他費用 | M6: 24210
A7: 2018 | B7: 3 | C7: 201803 | D7: Kelly Group | E7: 公隆化學股份有限公司 | F7: CPCRM05498 | G7: 專案-興勤電子 | H7: CustomerProject | I7: 成本累積 | J7: NASL12:電子化學課 | K7: Resource | L7: R03:交際費用 | M7: 1035 | Q7: Chris
A8: 2018 | B8: 3 | C8: 201803 | D8: Kelly Group | E8: 公隆化學股份有限公司 | F8: CPCRM10848 | G8: 專案-華新科技 | H8: CustomerProject | I8: 成本累積 | J8: NASL12:電子化學課 | K8: Resource | L8: R03:交際費用 | M8: 3526 | Q8: Chris
A9: 2018 | B9: 3 | C9: 201803 | D9: Kelly Group | E9: 公隆化學股份有限公司 | F9: CPCRM11533 | G9: 專案-國巨楠梓 | H9: CustomerProject | I9: 成本累積 | J9: NASL12:電子化學課 | K9: Resource | L9: R03:交際費用 | M9: 8493 | Q9: Chris
A10: 2018 | B10: 3 | C10: 201803 | D10: Kelly Group | E10: 公隆化學股份有限公司 | F10: CPunknow | G10: 專案-未分析顧客 | H10: CustomerProject | I10: 成本累積 | J10: NASL12:電子化學課 | K10: Resource | L10: R05:其他費用 | M10: 16648
A11: 2018 | B11: 3 | C11: 201803 | D11: Kelly Group | E11: 公隆化學股份有限公司 | F11: CPCRM00550 | G11: 專案-瑞興發 | H11: CustomerProject | I11: 成本累積 | J11: NASL11:製程化學課 | K11: Activity | L11: A05:拜訪新客戶 | M11: 1886.3913 | N11: =M11/ActivityCenter!$L$2 -> 48 | Q11: Ian
A12: 2018 | B12: 3 | C12: 201803 | D12: Kelly Group | E12: 公隆化學股份有限公司 | F12: CPCRM00783 | G12: 專案-亞洲漢威 | H12: CustomerProject | I12: 成本累積 | J12: NASL11:製程化學課 | K12: Activity | L12: A05:拜訪新客戶 | M12: 2279.3895 | N12: =M12/ActivityCenter!$L$2 -> 58 | Q12: Ian
A13: 2018 | B13: 3 | C13: 201803 | D13: Kelly Group | E13: 公隆化學股份有限公司 | F13: CPCRM00937 | G13: 專案-大勤化成 | H13: CustomerProject | I13: 成本累積 | J13: NASL11:製程化學課 | K13: Activity | L13: A07:推薦新產品 | M13: 18863.913 | N13: =M13/ActivityCenter!$L$2 -> 480 | Q13: Ian
A14: 2018 | B14: 3 | C14: 201803 | D14: Kelly Group | E14: 公隆化學股份有限公司 | F14: CPCRM01037 | G14: 專案-華邦電 | H14: CustomerProject | I14: 成本累積 | J14: NASL11:製程化學課 | K14: Activity | L14: A09:偕同技術服務 | M14: 8881.7591 | N14: =M14/ActivityCenter!$L$2 -> 226 | Q14: Ian
A15: 2018 | B15: 3 | C15: 201803 | D15: Kelly Group | E15: 公隆化學股份有限公司 | F15: CPCRM01042 | G15: 專案-欣銓科技 | H15: CustomerProject | I15: 成本累積 | J15: NASL11:製程化學課 | K15: Activity | L15: A09:偕同技術服務 | M15: 1650.5924 | N15: =M15/ActivityCenter!$L$2 -> 42 | Q15: Ian
A16: 2018 | B16: 3 | C16: 201803 | D16: Kelly Group | E16: 公隆化學股份有限公司 | F16: CPCRM01042 | G16: 專案-欣銓科技 | H16: CustomerProject | I16: 成本累積 | J16: NASL11:製程化學課 | K16: Activity | L16: A11:取樣分析 | M16: 3694.183 | N16: =M16/ActivityCenter!$L$2 -> 94 | Q16: Ian
A17: 2018 | B17: 3 | C17: 201803 | D17: Kelly Group | E17: 公隆化學股份有限公司 | F17: CPCRM01049 | G17: 專案-台星科 | H17: CustomerProject | I17: 成本累積 | J17: NASL11:製程化學課 | K17: Activity | L17: A09:偕同技術服務 | M17: 5698.4737 | N17: =M17/ActivityCenter!$L$2 -> 145 | Q17: Ian
A18: 2018 | B18: 3 | C18: 201803 | D18: Kelly Group | E18: 公隆化學股份有限公司 | F18: CPCRM01052 | G18: 專案-福懋科技 | H18: CustomerProject | I18: 成本累積 | J18: NASL11:製程化學課 | K18: Activity | L18: A09:偕同技術服務 | M18: 5384.0752 | N18: =M18/ActivityCenter!$L$2 -> 137 | Q18: Ian
A19: 2018 | B19: 3 | C19: 201803 | D19: Kelly Group | E19: 公隆化學股份有限公司 | F19: CPCRM01090 | G19: 專案-台弟工業 | H19: CustomerProject | I19: 成本累積 | J19: NASL11:製程化學課 | K19: Activity | L19: A09:偕同技術服務 | M19: 2633.0879 | N19: =M19/ActivityCenter!$L$2 -> 67 | Q19: Ian
A20: 2018 | B20: 3 | C20: 201803 | D20: Kelly Group | E20: 公隆化學股份有限公司 | F20: CPCRM01091 | G20: 專案-群浤科技 | H20: CustomerProject | I20: 成本累積 | J20: NASL11:製程化學課 | K20: Activity | L20: A09:偕同技術服務 | M20: 4991.077 | N20: =M20/ActivityCenter!$L$2 -> 127 | Q20: Ian
A21: 2018 | B21: 3 | C21: 201803 | D21: Kelly Group | E21: 公隆化學股份有限公司 | F21: CPCRM01091 | G21: 專案-群浤科技 | H21: CustomerProject | I21: 成本累積 | J21: NASL11:製程化學課 | K21: Activity | L21: A11:取樣分析 | M21: 4087.1812 | N21: =M21/ActivityCenter!$L$2 -> 104 | Q21: Ian
A22: 2018 | B22: 3 | C22: 201803 | D22: Kelly Group | E22: 公隆化學股份有限公司 | F22: CPCRM01093 | G22: 專案-巨品表面 | H22: CustomerProject | I22: 成本累積 | J22: NASL11:製程化學課 | K22: Activity | L22: A09:偕同技術服務 | M22: 2515.1884 | N22: =M22/ActivityCenter!$L$2 -> 64 | Q22: Ian
... A44: 2018 | B44: 3 | C44: 201803 | D44: Kelly Group | E44: 公隆化學股份有限公司 | F44: CP other cus | G44: 專案-other customer | H44: CustomerProject | I44: 成本累積 | J44: NASL11:製程化學課 | K44: Activity | L44: A18:Kelly內部事項 | M44: 226366.96 | N44: =M44/ActivityCenter!$L$2 -> 5760 | Q44: Clapton
A45: 2018 | B45: 3 | C45: 201803 | D45: Kelly Group | E45: 公隆化學股份有限公司 | F45: CPCRM10748 | G45: 專案-工研院 | H45: CustomerProject | I45: 成本累積 | J45: NASL12:電子化學課 | K45: Activity | L45: A04:專案追蹤 | M45: 1276.9887 | N45: =M45/ActivityCenter!$L$6 -> 133 | Q45: Louis
A46: 2018 | B46: 3 | C46: 201803 | D46: Kelly Group | E46: 公隆化學股份有限公司 | F46: CPCRM03863 | G46: 專案-致嘉科技 | H46: CustomerProject | I46: 成本累積 | J46: NASL12:電子化學課 | K46: Activity | L46: A05:拜訪新客戶 | M46: 2304.3406 | N46: =M46/ActivityCenter!$L$6 -> 240 | Q46: Chris
A47: 2018 | B47: 3 | C47: 201803 | D47: Kelly Group | E47: 公隆化學股份有限公司 | F47: CPCRM05498 | G47: 專案-興勤電子 | H47: CustomerProject | I47: 成本累積 | J47: NASL12:電子化學課 | K47: Activity | L47: A10:偕同原廠拜訪 | M47: 4608.6812 | N47: =M47/ActivityCenter!$L$6 -> 480 | Q47: Chris
A48: 2018 | B48: 3 | C48: 201803 | D48: Kelly Group | E48: 公隆化學股份有限公司 | F48: CPCRM08397 | G48: 專案-奇美實業 | H48: CustomerProject | I48: 成本累積 | J48: NASL12:電子化學課 | K48: Activity | L48: A03:爭取新專案 | M48: 3072.4541 | N48: =M48/ActivityCenter!$L$6 -> 320 | Q48: Chris
A49: 2018 | B49: 3 | C49: 201803 | D49: Kelly Group | E49: 公隆化學股份有限公司 | F49: CPCRM08411 | G49: 專案-新應材 | H49: CustomerProject | I49: 成本累積 | J49: NASL12:電子化學課 | K49: Activity | L49: A05:拜訪新客戶 | M49: 1344.1987 | N49: =M49/ActivityCenter!$L$6 -> 140 | Q49: Chris
A50: 2018 | B50: 3 | C50: 201803 | D50: Kelly Group | E50: 公隆化學股份有限公司 | F50: CPCRM08720 | G50: 專案-凱耀科技 | H50: CustomerProject | I50: 成本累積 | J50: NASL12:電子化學課 | K50: Activity | L50: A07:推薦新產品 | M50: 1536.2271 | N50: =M50/ActivityCenter!$L$6 -> 160 | Q50: Chris
A51: 2018 | B51: 3 | C51: 201803 | D51: Kelly Group | E51: 公隆化學股份有限公司 | F51: CPCRM10747 | G51: 專案-泓瀚科技 | H51: CustomerProject | I51: 成本累積 | J51: NASL12:電子化學課 | K51: Activity | L51: A04:專案追蹤 | M51: 2304.3406 | N51: =M51/ActivityCenter!$L$6 -> 240 | Q51: Chris
A52: 2018 | B52: 3 | C52: 201803 | D52: Kelly Group | E52: 公隆化學股份有限公司 | F52: CPCRM10771 | G52: 專案-勤凱-浚博 | H52: CustomerProject | I52: 成本累積 | J52: NASL12:電子化學課 | K52: Activity | L52: A10:偕同原廠拜訪 | M52: 2304.3406 | N52: =M52/ActivityCenter!$L$6 -> 240 | Q52: Chris
A53: 2018 | B53: 3 | C53: 201803 | D53: Kelly Group | E53: 公隆化學股份有限公司 | F53: CPCRM10826 | G53: 專案-道登電子 | H53: CustomerProject | I53: 成本累積 | J53: NASL12:電子化學課 | K53: Activity | L53: A10:偕同原廠拜訪 | M53: 2304.3406 | N53: =M53/ActivityCenter!$L$6 -> 240 | Q53: Chris
A54: 2018 | B54: 3 | C54: 201803 | D54: Kelly Group | E54: 公隆化學股份有限公司 | F54: CPCRM10848 | G54: 專案-華新科技 | H54: CustomerProject | I54: 成本累積 | J54: NASL12:電子化學課 | K54: Activity | L54: A09:偕同技術服務 | M54: 1022.5511 | N54: =M54/ActivityCenter!$L$6 -> 106.5 | Q54: Chris
A55: 2018 | B55: 3 | C55: 201803 | D55: Kelly Group | E55: 公隆化學股份有限公司 | F55: CPCRM10848 | G55: 專案-華新科技 | H55: CustomerProject | I55: 成本累積 | J55: NASL12:電子化學課 | K55: Activity | L55: A10:偕同原廠拜訪 | M55: 3326.8917 | N55: =M55/ActivityCenter!$L$6 -> 346.5 | Q55: Chris
A56: 2018 | B56: 3 | C56: 201803 | D56: Kelly Group | E56: 公隆化學股份有限公司 | F56: CPCRM10848 | G56: 專案-華新科技 | H56: CustomerProject | I56: 成本累積 | J56: NASL12:電子化學課 | K56: Activity | L56: A12:客服諮詢 | M56: 4608.6812 | N56: =M56/ActivityCenter!$L$6 -> 480 | Q56: Chris
... A105: 2018 | B105: 3 | C105: 201803 | D105: Kelly Group | E105: 公隆化學股份有限公司 | F105: CP永光二廠 | G105: 專案-永光二廠 | H105: CustomerProject | I105: 成本累積 | J105: NASL12:電子化學課 | K105: Activity | L105: A03:爭取新專案 | M105: 921.73624 | N105: =M105/ActivityCenter!$L$6 -> 96 | Q105: Louis
A106: 2018 | B106: 3 | C106: 201803 | D106: Kelly Group | E106: 公隆化學股份有限公司 | F106: CPCRM05498 | G106: 專案-興勤電子 | H106: CustomerProject | I106: 成本歸屬至產品 | J106: NASL12:電子化學課 | M106: -4608.6812 | O106: 88000428 | P106: 3 | Q106: Chris
A107: 2018 | B107: 3 | C107: 201803 | D107: Kelly Group | E107: 公隆化學股份有限公司 | F107: CPCRM05498 | G107: 專案-興勤電子 | H107: CustomerProject | I107: 成本歸屬至產品 | J107: NASL12:電子化學課 | M107: -1035 | O107: 88000428 | P107: 3 | Q107: Chris
A108: 2018 | B108: 3 | C108: 201803 | D108: Kelly Group | E108: 公隆化學股份有限公司 | F108: CPCRM10771 | G108: 專案-勤凱-浚博 | H108: CustomerProject | I108: 成本歸屬至產品 | J108: NASL12:電子化學課 | M108: -1241.5159 | O108: 88000411 | P108: 17 | Q108: Chris
A109: 2018 | B109: 3 | C109: 201803 | D109: Kelly Group | E109: 公隆化學股份有限公司 | F109: CPCRM10771 | G109: 專案-勤凱-浚博 | H109: CustomerProject | I109: 成本歸屬至產品 | J109: NASL12:電子化學課 | M109: -1062.8247 | O109: 88000413 | P109: 19 | Q109: Chris
A110: 2018 | B110: 3 | C110: 201803 | D110: Kelly Group | E110: 公隆化學股份有限公司 | F110: CPCRM10848 | G110: 專案-華新科技 | H110: CustomerProject | I110: 成本歸屬至產品 | J110: NASL12:電子化學課 | M110: -89.29176 | O110: 87000085 | P110: 17 | Q110: Chris
A111: 2018 | B111: 3 | C111: 201803 | D111: Kelly Group | E111: 公隆化學股份有限公司 | F111: CPCRM10848 | G111: 專案-華新科技 | H111: CustomerProject | I111: 成本歸屬至產品 | J111: NASL12:電子化學課 | M111: -106.65405 | O111: 88000407 | P111: 187 | Q111: Chris
A112: 2018 | B112: 3 | C112: 201803 | D112: Kelly Group | E112: 公隆化學股份有限公司 | F112: CPCRM10848 | G112: 專案-華新科技 | H112: CustomerProject | I112: 成本歸屬至產品 | J112: NASL12:電子化學課 | M112: -1654.9586 | O112: 88000407 | P112: 187 | Q112: Chris
A113: 2018 | B113: 3 | C113: 201803 | D113: Kelly Group | E113: 公隆化學股份有限公司 | F113: CPCRM10848 | G113: 專案-華新科技 | H113: CustomerProject | I113: 成本歸屬至產品 | J113: NASL12:電子化學課 | M113: -1195.3736 | O113: 88000426 | P113: 36 | Q113: Chris
A114: 2018 | B114: 3 | C114: 201803 | D114: Kelly Group | E114: 公隆化學股份有限公司 | F114: CPCRM11533 | G114: 專案-國巨楠梓 | H114: CustomerProject | I114: 成本歸屬至產品 | J114: NASL12:電子化學課 | M114: -453.10894 | O114: 88000423 | P114: 17 | Q114: Chris
A115: 2018 | B115: 3 | C115: 201803 | D115: Kelly Group | E115: 公隆化學股份有限公司 | F115: CPCRM11533 | G115: 專案-國巨楠梓 | H115: CustomerProject | I115: 成本歸屬至產品 | J115: NASL12:電子化學課 | M115: -828.68052 | O115: 88000426 | P115: 18 | Q115: Chris
A116: 2018 | B116: 3 | C116: 201803 | D116: Kelly Group | E116: 公隆化學股份有限公司 | F116: CPCRM11533 | G116: 專案-國巨楠梓 | H116: CustomerProject | I116: 成本歸屬至產品 | J116: NASL12:電子化學課 | M116: -1267.6868 | O116: 88000423 | P116: 17 | Q116: Chris
A117: 2018 | B117: 3 | C117: 201803 | D117: Kelly Group | E117: 公隆化學股份有限公司 | F117: CPCRM11533 | G117: 專案-國巨楠梓 | H117: CustomerProject | I117: 成本歸屬至產品 | J117: NASL12:電子化學課 | M117: -2318.4432 | O117: 88000426 | P117: 18 | Q117: Chris
... A134: 2018 | B134: 3 | C134: 201803 | D134: Kelly Group | E134: 公隆化學股份有限公司 | F134: CPCRM17296 | G134: 專案-台灣美磊 | H134: CustomerProject | I134: 成本歸屬至產品 | J134: NASL12:電子化學課 | M134: -1536.2271 | O134: 88000513 | P134: 16 | Q134: Chris
A135: 2018 | B135: 4 | C135: 201804 | D135: Kelly Group | E135: 公隆化學股份有限公司 | F135: CPunknow | G135: 專案-未分析顧客 | H135: CustomerProject | I135: 成本累積 | J135: NASL10:新事業開發部 | K135: Resource | L135: R05:其他費用 | M135: 3991
A136: 2018 | B136: 4 | C136: 201804 | D136: Kelly Group | E136: 公隆化學股份有限公司 | F136: CPCRM00400 | G136: 專案-東隆五金 | H136: CustomerProject | I136: 成本累積 | J136: NASL11:製程化學課 | K136: Resource | L136: R05:其他費用 | M136: 3500 | Q136: Vincent
A137: 2018 | B137: 4 | C137: 201804 | D137: Kelly Group | E137: 公隆化學股份有限公司 | F137: CPCRM00696 | G137: 專案-健達生物 | H137: CustomerProject | I137: 成本累積 | J137: NASL11:製程化學課 | K137: Resource | L137: R03:交際費用 | M137: 0 | Q137: Vincent
A138: 2018 | B138: 4 | C138: 201804 | D138: Kelly Group | E138: 公隆化學股份有限公司 | F138: CPCRM00696 | G138: 專案-健達生物 | H138: CustomerProject | I138: 成本累積 | J138: NASL11:製程化學課 | K138: Resource | L138: R04:樣品費 | M138: 0 | Q138: Vincent
A139: 2018 | B139: 4 | C139: 201804 | D139: Kelly Group | E139: 公隆化學股份有限公司 | F139: CPCRM00911 | G139: 專案-台灣鉅邁 | H139: CustomerProject | I139: 成本累積 | J139: NASL11:製程化學課 | K139: Resource | L139: R04:樣品費 | M139: 0 | Q139: Vincent
A140: 2018 | B140: 4 | C140: 201804 | D140: Kelly Group | E140: 公隆化學股份有限公司 | F140: CP華震科技 | G140: 專案-華震科技 | H140: CustomerProject | I140: 成本累積 | J140: NASL11:製程化學課 | K140: Resource | L140: R05:其他費用 | M140: 1500 | Q140: Ian
A141: 2018 | B141: 4 | C141: 201804 | D141: Kelly Group | E141: 公隆化學股份有限公司 | F141: CPunknow | G141: 專案-未分析顧客 | H141: CustomerProject | I141: 成本累積 | J141: NASL11:製程化學課 | K141: Resource | L141: R05:其他費用 | M141: 11664
A142: 2018 | B142: 4 | C142: 201804 | D142: Kelly Group | E142: 公隆化學股份有限公司 | F142: CPEMERSON | G142: 專案-EMERSON | H142: CustomerProject | I142: 成本累積 | J142: NASL11:製程化學課 | K142: Resource | L142: R05:其他費用 | M142: 1467 | Q142: Vincent
A143: 2018 | B143: 4 | C143: 201804 | D143: Kelly Group | E143: 公隆化學股份有限公司 | F143: CPCRM05498 | G143: 專案-興勤電子 | H143: CustomerProject | I143: 成本累積 | J143: NASL12:電子化學課 | K143: Resource | L143: R03:交際費用 | M143: 0 | Q143: Chris
A144: 2018 | B144: 4 | C144: 201804 | D144: Kelly Group | E144: 公隆化學股份有限公司 | F144: CPCRM10848 | G144: 專案-華新科技 | H144: CustomerProject | I144: 成本累積 | J144: NASL12:電子化學課 | K144: Resource | L144: R03:交際費用 | M144: 0 | Q144: Chris
A145: 2018 | B145: 4 | C145: 201804 | D145: Kelly Group | E145: 公隆化學股份有限公司 | F145: CPCRM10848 | G145: 專案-華新科技 | H145: CustomerProject | I145: 成本累積 | J145: NASL12:電子化學課 | K145: Resource | L145: R05:其他費用 | M145: 1600 | Q145: Chris
A146: 2018 | B146: 4 | C146: 201804 | D146: Kelly Group | E146: 公隆化學股份有限公司 | F146: CPCRM11533 | G146: 專案-國巨楠梓 | H146: CustomerProject | I146: 成本累積 | J146: NASL12:電子化學課 | K146: Resource | L146: R03:交際費用 | M146: 0 | Q146: Chris
A147: 2018 | B147: 4 | C147: 201804 | D147: Kelly Group | E147: 公隆化學股份有限公司 | F147: CPCRM17381 | G147: 專案-桃園-愛賽克 | H147: CustomerProject | I147: 成本累積 | J147: NASL12:電子化學課 | K147: Resource | L147: R03:交際費用 | M147: 535 | Q147: Chris
A148: 2018 | B148: 4 | C148: 201804 | D148: Kelly Group | E148: 公隆化學股份有限公司 | F148: CPCRM19822 | G148: 專案-友達 | H148: CustomerProject | I148: 成本累積 | J148: NASL12:電子化學課 | K148: Resource | L148: R05:其他費用 | M148: 3500 | Q148: Chris
A149: 2018 | B149: 4 | C149: 201804 | D149: Kelly Group | E149: 公隆化學股份有限公司 | F149: CPunknow | G149: 專案-未分析顧客 | H149: CustomerProject | I149: 成本累積 | J149: NASL12:電子化學課 | K149: Resource | L149: R05:其他費用 | M149: 5409
A150: 2018 | B150: 4 | C150: 201804 | D150: Kelly Group | E150: 公隆化學股份有限公司 | F150: CPCRM00550 | G150: 專案-瑞興發 | H150: CustomerProject | I150: 成本累積 | J150: NASL11:製程化學課 | K150: Activity | L150: A05:拜訪新客戶 | M150: 0 | N150: =M150/ActivityCenter!$L$10 -> 0 | Q150: Ian
A151: 2018 | B151: 4 | C151: 201804 | D151: Kelly Group | E151: 公隆化學股份有限公司 | F151: CPCRM00783 | G151: 專案-亞洲漢威 | H151: CustomerProject | I151: 成本累積 | J151: NASL11:製程化學課 | K151: Activity | L151: A05:拜訪新客戶 | M151: 0 | N151: =M151/ActivityCenter!$L$10 -> 0 | Q151: Ian
A152: 2018 | B152: 4 | C152: 201804 | D152: Kelly Group | E152: 公隆化學股份有限公司 | F152: CPCRM00937 | G152: 專案-大勤化成 | H152: CustomerProject | I152: 成本累積 | J152: NASL11:製程化學課 | K152: Activity | L152: A07:推薦新產品 | M152: 0 | N152: =M152/ActivityCenter!$L$10 -> 0 | Q152: Ian
A153: 2018 | B153: 4 | C153: 201804 | D153: Kelly Group | E153: 公隆化學股份有限公司 | F153: CPCRM01037 | G153: 專案-華邦電 | H153: CustomerProject | I153: 成本累積 | J153: NASL11:製程化學課 | K153: Activity | L153: A09:偕同技術服務 | M153: 0 | N153: =M153/ActivityCenter!$L$10 -> 0 | Q153: Ian
A154: 2018 | B154: 4 | C154: 201804 | D154: Kelly Group | E154: 公隆化學股份有限公司 | F154: CPCRM01037 | G154: 專案-華邦電 | H154: CustomerProject | I154: 成本累積 | J154: NASL11:製程化學課 | K154: Activity | L154: A11:取樣分析 | M154: 1129.1181 | N154: =M154/ActivityCenter!$L$10 -> 15 | Q154: Ian
A155: 2018 | B155: 4 | C155: 201804 | D155: Kelly Group | E155: 公隆化學股份有限公司 | F155: CPCRM01042 | G155: 專案-欣銓科技 | H155: CustomerProject | I155: 成本累積 | J155: NASL11:製程化學課 | K155: Activity | L155: A09:偕同技術服務 | M155: 0 | N155: =M155/ActivityCenter!$L$10 -> 0 | Q155: Ian
A156: 2018 | B156: 4 | C156: 201804 | D156: Kelly Group | E156: 公隆化學股份有限公司 | F156: CPCRM01042 | G156: 專案-欣銓科技 | H156: CustomerProject | I156: 成本累積 | J156: NASL11:製程化學課 | K156: Activity | L156: A11:取樣分析 | M156: 0 | N156: =M156/ActivityCenter!$L$10 -> 0 | Q156: Ian
A157: 2018 | B157: 4 | C157: 201804 | D157: Kelly Group | E157: 公隆化學股份有限公司 | F157: CPCRM01046 | G157: 專案-華泰電子 | H157: CustomerProject | I157: 成本累積 | J157: NASL11:製程化學課 | K157: Activity | L157: A19:目標客戶拜訪 | M157: 4140.0995 | N157: =M157/ActivityCenter!$L$10 -> 55 | Q157: Ian
A158: 2018 | B158: 4 | C158: 201804 | D158: Kelly Group | E158: 公隆化學股份有限公司 | F158: CPCRM01049 | G158: 專案-台星科 | H158: CustomerProject | I158: 成本累積 | J158: NASL11:製程化學課 | K158: Activity | L158: A09:偕同技術服務 | M158: 0 | N158: =M158/ActivityCenter!$L$10 -> 0 | Q158: Ian
A159: 2018 | B159: 4 | C159: 201804 | D159: Kelly Group | E159: 公隆化學股份有限公司 | F159: CPCRM01052 | G159: 專案-福懋科技 | H159: CustomerProject | I159: 成本累積 | J159: NASL11:製程化學課 | K159: Activity | L159: A09:偕同技術服務 | M159: 0 | N159: =M159/ActivityCenter!$L$10 -> 0 | Q159: Ian
A160: 2018 | B160: 4 | C160: 201804 | D160: Kelly Group | E160: 公隆化學股份有限公司 | F160: CPCRM01053 | G160: 專案-渼豐表面處理 | H160: CustomerProject | I160: 成本累積 | J160: NASL11:製程化學課 | K160: Activity | L160: A09:偕同技術服務 | M160: 7602.7282 | N160: =M160/ActivityCenter!$L$10 -> 101 | Q160: Ian
A161: 2018 | B161: 4 | C161: 201804 | D161: Kelly Group | E161: 公隆化學股份有限公司 | F161: CPCRM01090 | G161: 專案-台弟工業 | H161: CustomerProject | I161: 成本累積 | J161: NASL11:製程化學課 | K161: Activity | L161: A09:偕同技術服務 | M161: 0 | N161: =M161/ActivityCenter!$L$10 -> 0 | Q161: Ian
... A206: 2018 | B206: 4 | C206: 201804 | D206: Kelly Group | E206: 公隆化學股份有限公司 | F206: CP other cus | G206: 專案-other customer | H206: CustomerProject | I206: 成本累積 | J206: NASL11:製程化學課 | K206: Activity | L206: A18:Kelly內部事項 | M206: 361317.78 | N206: =M206/ActivityCenter!$L$10 -> 4800 | Q206: Clapton
A207: 2018 | B207: 4 | C207: 201804 | D207: Kelly Group | E207: 公隆化學股份有限公司 | F207: CPCRM10748 | G207: 專案-工研院 | H207: CustomerProject | I207: 成本累積 | J207: NASL12:電子化學課 | K207: Activity | L207: A02:市場動態 | M207: 4889.0182 | N207: =M207/ActivityCenter!$L$14 -> 384 | Q207: Louis
A208: 2018 | B208: 4 | C208: 201804 | D208: Kelly Group | E208: 公隆化學股份有限公司 | F208: CPCRM10748 | G208: 專案-工研院 | H208: CustomerProject | I208: 成本累積 | J208: NASL12:電子化學課 | K208: Activity | L208: A04:專案追蹤 | M208: 0 | N208: =M208/ActivityCenter!$L$14 -> 0 | Q208: Louis
A209: 2018 | B209: 4 | C209: 201804 | D209: Kelly Group | E209: 公隆化學股份有限公司 | F209: CPCRM20308 | G209: 專案-九怡工業 | H209: CustomerProject | I209: 成本累積 | J209: NASL12:電子化學課 | K209: Activity | L209: A05:拜訪新客戶 | M209: 1222.2545 | N209: =M209/ActivityCenter!$L$14 -> 96 | Q209: Louis
A210: 2018 | B210: 4 | C210: 201804 | D210: Kelly Group | E210: 公隆化學股份有限公司 | F210: CPCRM20308 | G210: 專案-九怡工業 | H210: CustomerProject | I210: 成本累積 | J210: NASL12:電子化學課 | K210: Activity | L210: A22:帳款收回 | M210: 802.10455 | N210: =M210/ActivityCenter!$L$14 -> 63 | Q210: Louis
A211: 2018 | B211: 4 | C211: 201804 | D211: Kelly Group | E211: 公隆化學股份有限公司 | F211: CPCRM03863 | G211: 專案-致嘉科技 | H211: CustomerProject | I211: 成本累積 | J211: NASL12:電子化學課 | K211: Activity | L211: A05:拜訪新客戶 | M211: 0 | N211: =M211/ActivityCenter!$L$14 -> 0 | Q211: Chris
A212: 2018 | B212: 4 | C212: 201804 | D212: Kelly Group | E212: 公隆化學股份有限公司 | F212: CPCRM05197 | G212: 專案-聯致科技 | H212: CustomerProject | I212: 成本累積 | J212: NASL12:電子化學課 | K212: Activity | L212: A04:專案追蹤 | M212: 3055.6364 | N212: =M212/ActivityCenter!$L$14 -> 240 | Q212: Chris
A213: 2018 | B213: 4 | C213: 201804 | D213: Kelly Group | E213: 公隆化學股份有限公司 | F213: CPCRM05498 | G213: 專案-興勤電子 | H213: CustomerProject | I213: 成本累積 | J213: NASL12:電子化學課 | K213: Activity | L213: A03:爭取新專案 | M213: 3654.0318 | N213: =M213/ActivityCenter!$L$14 -> 287 | Q213: Chris
A214: 2018 | B214: 4 | C214: 201804 | D214: Kelly Group | E214: 公隆化學股份有限公司 | F214: CPCRM05498 | G214: 專案-興勤電子 | H214: CustomerProject | I214: 成本累積 | J214: NASL12:電子化學課 | K214: Activity | L214: A10:偕同原廠拜訪 | M214: 0 | N214: =M214/ActivityCenter!$L$14 -> 0 | Q214: Chris
A215: 2018 | B215: 4 | C215: 201804 | D215: Kelly Group | E215: 公隆化學股份有限公司 | F215: CPCRM08397 | G215: 專案-奇美實業 | H215: CustomerProject | I215: 成本累積 | J215: NASL12:電子化學課 | K215: Activity | L215: A03:爭取新專案 | M215: 0 | N215: =M215/ActivityCenter!$L$14 -> 0 | Q215: Chris
A216: 2018 | B216: 4 | C216: 201804 | D216: Kelly Group | E216: 公隆化學股份有限公司 | F216: CPCRM08411 | G216: 專案-新應材 | H216: CustomerProject | I216: 成本累積 | J216: NASL12:電子化學課 | K216: Activity | L216: A02:市場動態 | M216: 2024.3591 | N216: =M216/ActivityCenter!$L$14 -> 159 | Q216: Chris
A217: 2018 | B217: 4 | C217: 201804 | D217: Kelly Group | E217: 公隆化學股份有限公司 | F217: CPCRM08411 | G217: 專案-新應材 | H217: CustomerProject | I217: 成本累積 | J217: NASL12:電子化學課 | K217: Activity | L217: A05:拜訪新客戶 | M217: 0 | N217: =M217/ActivityCenter!$L$14 -> 0 | Q217: Chris
A218: 2018 | B218: 4 | C218: 201804 | D218: Kelly Group | E218: 公隆化學股份有限公司 | F218: CPCRM08704 | G218: 專案-肯美特 | H218: CustomerProject | I218: 成本累積 | J218: NASL12:電子化學課 | K218: Activity | L218: A03:爭取新專案 | M218: 3908.6682 | N218: =M218/ActivityCenter!$L$14 -> 307 | Q218: Chris
... A307: 2018 | B307: 4 | C307: 201804 | D307: Kelly Group | E307: 公隆化學股份有限公司 | F307: CP微鑽石 | G307: 專案-微鑽石 | H307: CustomerProject | I307: 成本累積 | J307: NASL12:電子化學課 | K307: Activity | L307: A05:拜訪新客戶 | M307: 1566.0136 | N307: =M307/ActivityCenter!$L$14 -> 123 | Q307: Louis
A308: 2018 | B308: 4 | C308: 201804 | D308: Kelly Group | E308: 公隆化學股份有限公司 | F308: CPCRM00783 | G308: 專案-亞洲漢威 | H308: CustomerProject | I308: 成本歸屬至產品 | J308: NASL11:製程化學課 | M308: -218.38329 | O308: 72000045 | P308: 19.7 | Q308: Ian
A309: 2018 | B309: 4 | C309: 201804 | D309: Kelly Group | E309: 公隆化學股份有限公司 | F309: CP華震科技 | G309: 專案-華震科技 | H309: CustomerProject | I309: 成本歸屬至產品 | J309: NASL11:製程化學課 | M309: -275.10917 | O309: 61000027 | P309: 240 | Q309: Ian
A310: 2018 | B310: 4 | C310: 201804 | D310: Kelly Group | E310: 公隆化學股份有限公司 | F310: CP華震科技 | G310: 專案-華震科技 | H310: CustomerProject | I310: 成本歸屬至產品 | J310: NASL11:製程化學課 | M310: -275.10917 | O310: 61000027 | P310: 240 | Q310: Ian
A311: 2018 | B311: 4 | C311: 201804 | D311: Kelly Group | E311: 公隆化學股份有限公司 | F311: CP華震科技 | G311: 專案-華震科技 | H311: CustomerProject | I311: 成本歸屬至產品 | J311: NASL11:製程化學課 | M311: -13726.92 | O311: 61000017 | P311: 500 | Q311: Ian
A312: 2018 | B312: 4 | C312: 201804 | D312: Kelly Group | E312: 公隆化學股份有限公司 | F312: CP華震科技 | G312: 專案-華震科技 | H312: CustomerProject | I312: 成本歸屬至產品 | J312: NASL11:製程化學課 | M312: -9151.28 | O312: 61000017 | P312: 500 | Q312: Ian
A313: 2018 | B313: 4 | C313: 201804 | D313: Kelly Group | E313: 公隆化學股份有限公司 | F313: CP華震科技 | G313: 專案-華震科技 | H313: CustomerProject | I313: 成本歸屬至產品 | J313: NASL11:製程化學課 | M313: -6626.7889 | O313: 61000027 | P313: 240 | Q313: Ian
A314: 2018 | B314: 4 | C314: 201804 | D314: Kelly Group | E314: 公隆化學股份有限公司 | F314: CP華震科技 | G314: 專案-華震科技 | H314: CustomerProject | I314: 成本歸屬至產品 | J314: NASL11:製程化學課 | M314: -6626.7889 | O314: 61000027 | P314: 240 | Q314: Ian
A315: 2018 | B315: 4 | C315: 201804 | D315: Kelly Group | E315: 公隆化學股份有限公司 | F315: CP華震科技 | G315: 專案-華震科技 | H315: CustomerProject | I315: 成本歸屬至產品 | J315: NASL11:製程化學課 | M315: -569.869 | O315: 61000017 | P315: 500 | Q315: Ian
A316: 2018 | B316: 4 | C316: 201804 | D316: Kelly Group | E316: 公隆化學股份有限公司 | F316: CP華震科技 | G316: 專案-華震科技 | H316: CustomerProject | I316: 成本歸屬至產品 | J316: NASL11:製程化學課 | M316: -379.91266 | O316: 61000017 | P316: 500 | Q316: Ian
A317: 2018 | B317: 4 | C317: 201804 | D317: Kelly Group | E317: 公隆化學股份有限公司 | F317: CPCRM00783 | G317: 專案-亞洲漢威 | H317: CustomerProject | I317: 成本歸屬至產品 | J317: NASL11:製程化學課 | M317: -2061.0062 | O317: 74000246 | P317: 232.4 | Q317: Ian
...

Sheet 專案成本
B3: Column Labels
B4: 3 | D4: 5 | F4: 4 | H4: Total 加總 - 實際產能(分鐘) | I4: Total 加總 - 金額
A5: Row Labels | B5: 加總 - 實際產能(分鐘) | C5: 加總 - 金額 | D5: 加總 - 實際產能(分鐘) | E5: 加總 - 金額 | F5: 加總 - 實際產能(分鐘) | G5: 加總 - 金額
A6: NASL12:電子化學課 | B6: 13486 | C6: 98299.329 | D6: 10080 | E6: 72182.856 | F6: 8160 | G6: 84526.805 | H6: 31726 | I6: 255008.99
A7: Louis | B7: 6219 | C7: 59711.226 | D7: 3928 | E7: 32495.218 | F7: 4017 | G7: 43377.305 | H7: 14164 | I7: 135583.75
A8: 專案-九怡工業 | D8: 0 | E8: 0 | F8: 159 | G8: -1.1368684e-13 | H8: 159 | I8: -1.1368684e-13
A9: 專案-三德 | D9: 0 | E9: 0 | F9: 82 | G9: 1044.0091 | H9: 82 | I9: 1044.0091 | K9: louis 正在進行的專案有44個
A10: 專案-大格化學 | B10: 194 | C10: 1862.6753 | D10: 180 | E10: 1489.0884 | F10: 0 | G10: 0 | H10: 374 | I10: 3351.7637 | K10: chris 正在進行的專案有41個
A11: 專案-山鶯欣興電子 | B11: 580 | C11: 5568.8231 | D11: 0 | E11: 0 | F11: 0 | G11: 0 | H11: 580 | I11: 5568.8231 | K11: Ian 正在進行的專案有47個
A12: 專案-川裕工業 | B12: 230 | C12: 2208.3264 | D12: 0 | E12: 0 | F12: 0 | G12: 0 | H12: 230 | I12: 2208.3264
A13: 專案-工研院 | B13: 133 | C13: 1276.9887 | D13: 0 | E13: 0 | F13: 384 | G13: 4889.0182 | H13: 517 | I13: 6166.0069
A14: 專案-友輝光電 | B14: 480 | C14: 4608.6812 | D14: 0 | E14: 0 | F14: 0 | G14: 0 | H14: 480 | I14: 4608.6812
A15: 專案-台虹科技 | B15: 160 | C15: 1536.2271 | D15: 0 | E15: 0 | F15: 0 | G15: 0 | H15: 160 | I15: 1536.2271
A16: 專案-台灣同欣 | D16: 0 | E16: 0 | F16: 82 | G16: 0 | H16: 82 | I16: 0
A17: 專案-台灣奈晶 | B17: 465 | C17: 4464.6599 | D17: 0 | E17: 0 | F17: 0 | G17: 0 | H17: 465 | I17: 4464.6599
A18: 專案-台灣-捷能材料 | D18: 5 | E18: 41.363567 | H18: 5 | I18: 41.363567
A19: 專案-台灣優瑪 | D19: 192 | E19: 1588.361 | H19: 192 | I19: 1588.361
A20: 專案-永光二廠 | B20: 96 | C20: 921.73624 | D20: 0 | E20: 0 | F20: 0 | G20: 0 | H20: 96 | I20: 921.73624
A21: 專案-永光三廠 | B21: 192 | C21: 1843.4725 | D21: 0 | E21: 0 | F21: 0 | G21: 0 | H21: 192 | I21: 1843.4725
A22: 專案-永光化學 | D22: 400 | E22: 3309.0854 | F22: 369 | G22: 0 | H22: 769 | I22: 3309.0854
A23: 專案-永明泰 | D23: 0 | E23: 0 | F23: 125 | G23: 1591.4773 | H23: 125 | I23: 1591.4773
A24: 專案-竹北凱鍶 | B24: 160 | C24: 1536.2271 | D24: 0 | E24: 0 | F24: 288 | G24: 3666.7636 | H24: 448 | I24: 5202.9907
A25: 專案-和蓮光電 | D25: 192 | E25: 1588.361 | H25: 192 | I25: 1588.361
A26: 專案-忠信汽車 | D26: 96 | E26: 794.18049 | H26: 96 | I26: 794.18049
A27: 專案-林口南亞科 | B27: 141 | C27: 1353.8001 | D27: 0 | E27: 0 | F27: 0 | G27: 0 | H27: 141 | I27: 1353.8001
A28: 專案-林口穩懋 | B28: 45 | C28: 432.06386 | D28: 160 | E28: 1323.6341 | F28: 0 | G28: 0 | H28: 205 | I28: 1755.698
A29: 專案-矽恩特殊材料 | B29: 190 | C29: 1824.2696 | D29: 0 | E29: 0 | F29: 214 | G29: 2724.6091 | H29: 404 | I29: 4548.8787
A30: 專案-肥特補 | D30: 0 | E30: 0 | F30: 221 | G30: 2813.7318 | H30: 221 | I30: 2813.7318
A31: 專案-金順億 | D31: 120 | E31: 992.72561 | H31: 120 | I31: 992.72561
A32: 專案-長春-乾膜 | B32: 78 | C32: 748.91069 | D32: 440 | E32: 3639.9939 | F32: 258 | G32: 3284.8091 | H32: 776 | I32: 7673.7137
A33: 專案-洤順科技 | B33: 246 | C33: 2361.9491 | D33: 0 | E33: 0 | F33: 0 | G33: 0 | H33: 246 | I33: 2361.9491
A34: 專案-桃園-宸鴻 | B34: 206 | C34: 1977.8923 | D34: 160 | E34: 1323.6341 | F34: 0 | G34: 0 | H34: 366 | I34: 3301.5265
A35: 專案-創毅國際 | B35: 281 | C35: 2697.9988 | D35: 0 | E35: 0 | F35: 0 | G35: 0 | H35: 281 | I35: 2697.9988
A36: 專案-晶呈科技 | D36: 192 | E36: 1588.361 | H36: 192 | I36: 1588.361
A37: 專案-微鑽石 | D37: 0 | E37: 0 | F37: 123 | G37: 1566.0136 | H37: 123 | I37: 1566.0136
A38: 專案-愛迪克 | B38: 15 | C38: 144.02129 | D38: 0 | E38: 0 | F38: 0 | G38: 0 | H38: 15 | I38: 144.02129
A39: 專案-新北市-富致科技 | D39: 192 | E39: 1588.361 | F39: 165 | G39: 2100.75 | H39: 357 | I39: 3689.111
A40: 專案-新竹互力 | B40: 214 | C40: 2054.7037 | D40: 259 | E40: 2142.6328 | F40: 0 | G40: 0 | H40: 473 | I40: 4197.3365
A41: 專案-新竹光聚合 | B41: 133 | C41: 1276.9887 | D41: 240 | E41: 1985.4512 | F41: 222 | G41: 2826.4636 | H41: 595 | I41: 6088.9036
A42: 專案-瑞化 | B42: 95 | C42: 912.13482 | D42: 0 | E42: 0 | F42: 0 | G42: 0 | H42: 95 | I42: 912.13482
A43: 專案-群創_竹南 | D43: 0 | E43: 0 | F43: 142 | G43: 1807.9182 | H43: 142 | I43: 1807.9182
A44: 專案-群越 | D44: 640 | E44: 5294.5366 | H44: 640 | I44: 5294.5366
A45: 專案-達興 | B45: 480 | C45: 4608.6812 | D45: 0 | E45: 0 | F45: 386 | G45: 4914.4818 | H45: 866 | I45: 9523.163
A46: 專案-綠固 | B46: 640 | C46: 6144.9083 | D46: 160 | E46: 1323.6341 | F46: 0 | G46: 0 | H46: 800 | I46: 7468.5424
A47: 專案-遠呈科技 | D47: 0 | E47: 0 | F47: 491 | G47: 6251.3227 | H47: 491 | I47: 6251.3227
A48: 專案-億光 | D48: 180 | E48: 1489.0884 | H48: 180 | I48: 1489.0884
A49: 專案-廣達電腦 | B49: 480 | C49: 4608.6812 | D49: 120 | E49: 992.72561 | F49: 199 | G49: 2533.6318 | H49: 799 | I49: 8135.0386
A50: 專案-樹林台電研究所 | B50: 285 | C50: 2736.4045 | D50: 0 | E50: 0 | F50: 107 | G50: 1362.3045 | H50: 392 | I50: 4098.709
A51: Chris | B51: 7267 | C51: 38588.104 | D51: 6152 | E51: 39687.638 | F51: 4143 | G51: 41149.5 | H51: 17562 | I51: 119425.24
A52: 專案-友達 | D52: 0 | E52: 0 | F52: 432 | G52: 0 | H52: 432 | I52: 0
A53: 專案-天成 | D53: 160 | E53: 1323.6341 | H53: 160 | I53: 1323.6341
A54: 專案-台灣艾華電子 | B54: 71 | C54: 681.70076 | D54: 0 | E54: 0 | F54: 0 | G54: 0 | H54: 71 | I54: 681.70076
A55: 專案-台灣-杜邦 | D55: 720 | E55: 5956.3537 | F55: 160 | G55: 2037.0909 | H55: 880 | I55: 7993.4446
A56: 專案-台灣美磊 | B56: 160 | C56: 0 | D56: 160 | E56: 1323.6341 | F56: 240 | G56: 3055.6364 | H56: 560 | I56: 4379.2705
A57: 專案-台灣得力 | B57: 137 | C57: 1315.3944 | D57: 0 | E57: 0 | F57: 0 | G57: 0 | H57: 137 | I57: 1315.3944
A58: 專案-永勝光學 | D58: 0 | E58: 0 | F58: 173 | G58: 2202.6045 | H58: 173 | I58: 2202.6045
A59: 專案-永源 | B59: 928 | C59: 0 | D59: 400 | E59: 3309.0854 | F59: 0 | G59: 0 | H59: 1328 | I59: 3309.0854
A60: 專案-光洋科 | D60: 0 | E60: 0 | F60: 199 | G60: 2533.6318 | H60: 199 | I60: 2533.6318
A61: 專案-安炬 | D61: 480 | E61: 3970.9024 | H61: 480 | I61: 3970.9024
A62: 專案-汐止研究所(公隆化學) | D62: 480 | E62: 3970.9024 | H62: 480 | I62: 3970.9024
A63: 專案-志廣光電 | D63: 160 | E63: 1323.6341 | H63: 160 | I63: 1323.6341
A64: 專案-佳邦 | B64: 240 | C64: 2304.3406 | D64: 240 | E64: 1985.4512 | F64: 0 | G64: 0 | H64: 480 | I64: 4289.7918
A65: 專案-奇美實業 | B65: 320 | C65: 3072.4541 | D65: 288 | E65: -3072.4541 | F65: 0 | G65: 0 | H65: 608 | I65: 0
A66: 專案-昇陽光電 | B66: 529 | C66: 5079.1507 | D66: 216 | E66: 1786.9061 | F66: 0 | G66: 0 | H66: 745 | I66: 6866.0568
A67: 專案-泓瀚科技 | B67: 240 | C67: 2304.3406 | D67: 0 | E67: 0 | F67: 0 | G67: 0 | H67: 240 | I67: 2304.3406
A68: 專案-肯美特 | D68: 0 | E68: 0 | F68: 307 | G68: 3908.6682 | H68: 307 | I68: 3908.6682
A69: 專案-冠品 | D69: 0 | E69: 0 | F69: 160 | G69: 2037.0909 | H69: 160 | I69: 2037.0909
A70: 專案-恆橋 | D70: 160 | E70: 1323.6341 | H70: 160 | I70: 1323.6341
A71: 專案-致嘉科技 | B71: 240 | C71: 2304.3406 | D71: 0 | E71: 0 | F71: 0 | G71: 0 | H71: 240 | I71: 2304.3406
A72: 專案-苗栗-友晁 | B72: 240 | C72: 2304.3406 | D72: 0 | E72: 0 | F72: 0 | G72: 0 | H72: 240 | I72: 2304.3406
A73: 專案-桃園-愛賽克 | D73: 0 | E73: 0 | F73: 400 | G73: 5627.7273 | H73: 400 | I73: 5627.7273
A74: 專案-國巨楠梓 | B74: 507 | C74: 0 | D74: 0 | E74: 0 | F74: 0 | G74: 0 | H74: 507 | I74: 0
A75: 專案-崇越科技 | B75: 137 | C75: 1315.3944 | D75: 640 | E75: 5294.5366 | F75: 0 | G75: 0 | H75: 777 | I75: 6609.931
A76: 專案-凱耀科技 | B76: 160 | C76: 1536.2271 | D76: 0 | E76: 0 | F76: 192 | G76: 2444.5091 | H76: 352 | I76: 3980.7362
A77: 專案-華新科技 | B77: 933 | C77: 1.5916157e-12 | D77: 320 | E77: 2647.2683 | F77: 0 | G77: 1.1368684e-13 | H77: 1253 | I77: 2647.2683
A78: 專案-賀力氏 | D78: 0 | E78: 0 | F78: 160 | G78: 2037.0909 | H78: 160 | I78: 2037.0909
A79: 專案-黑德爾 | D79: 240 | E79: 1985.4512 | H79: 240 | I79: 1985.4512
A80: 專案-勤凱-浚博 | B80: 240 | C80: 0 | D80: 0 | E80: 0 | F80: 193 | G80: 2457.2409 | H80: 433 | I80: 2457.2409
A81: 專案-新竹-國碩 | B81: 421 | C81: 4042.1975 | D81: 0 | E81: 0 | F81: 0 | G81: 0 | H81: 421 | I81: 4042.1975
A82: 專案-新竹-錸德 | B82: 298 | C82: 2861.2229 | D82: 0 | E82: 0 | F82: 0 | G82: 0 | H82: 298 | I82: 2861.2229
A83: 專案-新應材 | B83: 140 | C83: 1344.1987 | D83: 288 | E83: -3368.5578 | F83: 159 | G83: 2024.3591 | H83: 587 | I83: 0
A84: 專案-道登電子 | B84: 240 | C84: 2304.3406 | D84: 0 | E84: 0 | F84: 0 | G84: 0 | H84: 240 | I84: 2304.3406
A85: 專案-達方電子 | D85: 0 | E85: 0 | F85: 281 | G85: 0 | H85: 281 | I85: 0
A86: 專案-達邁 | D86: 0 | E86: 0 | F86: 160 | G86: 2037.0909 | H86: 160 | I86: 2037.0909
A87: 專案-臻鼎 | D87: 0 | E87: 0 | F87: 160 | G87: 2037.0909 | H87: 160 | I87: 2037.0909
A88: 專案-興勤電子 | B88: 480 | C88: 0 | D88: 240 | E88: 1985.4512 | F88: 287 | G88: 3654.0318 | H88: 1007 | I88: 5639.483
A89: 專案-優陽科技 | B89: 447 | C89: 4291.8344 | D89: 720 | E89: 5956.3537 | F89: 0 | G89: 0 | H89: 1167 | I89: 10248.188
A90: 專案-瞬茂 | B90: 159 | C90: 1526.6256 | D90: 0 | E90: 0 | F90: 0 | G90: 0 | H90: 159 | I90: 1526.6256
A91: 專案-聯致科技 | D91: 240 | E91: 1985.4512 | F91: 240 | G91: 0 | H91: 480 | I91: 1985.4512
A92: 專案-覆晶光電 | D92: 0 | E92: 0 | F92: 240 | G92: 3055.6364 | H92: 240 | I92: 3055.6364
A93: NASL11:製程化學課 | B93: 5280 | C93: 217525.04 | D93: 4320 | E93: 210145.85 | F93: 3840 | G93: 206491.47 | H93: 13440 | I93: 634162.37
A94: Ian | B94: 5280 | C94: 207503.04 | D94: 3953 | E94: 180670.02 | F94: 3360 | G94: 201524.47 | H94: 12593 | I94: 589697.54
A95: 專案-kelly實驗室 | B95: 480 | C95: 18863.913 | D95: 0 | E95: 0 | F95: 0 | G95: 0 | H95: 480 | I95: 18863.913
A96: 專案-大發金屬 | D96: 69 | E96: 3429.2869 | F96: 171 | G96: 12871.946 | H96: 240 | I96: 16301.233
A97: 專案-大勤化成 | B97: 480 | C97: 18863.913 | D97: 0 | E97: 0 | F97: 0 | G97: 0 | H97: 480 | I97: 18863.913
A98: 專案-日月展金屬 | D98: 0 | E98: 0 | F98: 72 | G98: 5419.7667 | H98: 72 | I98: 5419.7667
A99: 專案-世豐螺絲 | D99: 17 | E99: 844.89678 | F99: 119 | G99: 8957.6699 | H99: 136 | I99: 9802.5667
A100: 專案-台弟工業 | B100: 67 | C100: 2633.0879 | D100: 0 | E100: 0 | F100: 0 | G100: 0 | H100: 67 | I100: 2633.0879
A101: 專案-台星科 | B101: 145 | C101: 5698.4737 | D101: 0 | E101: 0 | F101: 0 | G101: 0 | H101: 145 | I101: 5698.4737
A102: 專案-台灣京濱化 | D102: 0 | E102: 0 | F102: 155 | G102: 11667.553 | H102: 155 | I102: 11667.553
...

Sheet IncomeStatment
A1: 年 | B1: 月份 | C1: 公司代碼 | D1: 作業中心代碼 | E1: 訂單編號 | F1: 產品 | G1: 數量 | H1: 金額 | I1: 總銷貨成本 | J1: 製造成本 | K1: 客戶利潤 | L1: 產品利潤 | M1: 業務工程師
A2: 2018 | B2: 3 | C2: Kelly Group | D2: NASL12 | E2: Order01 | F2: 87000189 | G2: 72 | H2: 30600 | I2: 14564 | J2: 14564 | K2: 16036 | L2: 16036 | M2: Louis
A3: 2018 | B3: 3 | C3: Kelly Group | D3: NASL11 | E3: Order02 | F3: 74000242 | G3: 36 | H3: 16200 | I3: 13292 | J3: 13292 | K3: 2908 | L3: 2908 | M3: Vincent
A4: 2018 | B4: 3 | C4: Kelly Group | D4: NASL11 | E4: Order03 | F4: 74000158 | G4: 428 | H4: 74900 | I4: 44091 | J4: 44091 | K4: 30809 | L4: 30809 | M4: Vincent
A5: 2018 | B5: 3 | C5: Kelly Group | D5: NASL11 | E5: Order04 | F5: 74000063 | G5: 20 | H5: 9600 | I5: 4592 | J5: 4592 | K5: 5008 | L5: 5008 | M5: Vincent
A6: 2018 | B6: 3 | C6: Kelly Group | D6: NASL11 | E6: Order05 | F6: 71000576 | G6: 20 | H6: 6400 | I6: 2637 | J6: 2637 | K6: 3763 | L6: 3763 | M6: Vincent
A7: 2018 | B7: 3 | C7: Kelly Group | D7: NASL11 | E7: Order06 | F7: 74000162 | G7: 1000 | H7: 125000 | I7: 71469 | J7: 71469 | K7: 53531 | L7: 53531 | M7: Vincent
A8: 2018 | B8: 3 | C8: Kelly Group | D8: NASL12 | E8: Order07 | F8: 88000513 | G8: 16 | H8: 15360 | I8: 0 | K8: 15360 | L8: 15360 | M8: Chris
A9: 2018 | B9: 3 | C9: Kelly Group | D9: NASL12 | E9: Order07 | F9: 88000513 | G9: 16 | H9: 15360 | I9: 5248 | J9: 5248 | K9: 10112 | L9: 10112 | M9: Chris
A10: 2018 | B10: 3 | C10: Kelly Group | D10: NASL11 | E10: Order08 | F10: 74000193 | G10: 415.6 | H10: 60000 | I10: 33664 | J10: 33664 | K10: 26336 | L10: 26336 | M10: Vincent
A11: 2018 | B11: 3 | C11: Kelly Group | D11: NASL12 | E11: Order09 | F11: 87000182 | G11: 45 | H11: 60210 | I11: 40292 | J11: 40292 | K11: 19918 | L11: 19918 | M11: Chris
A12: 2018 | B12: 3 | C12: Kelly Group | D12: NASL12 | E12: Order10 | F12: 87000175 | G12: 26 | H12: 27066 | I12: 18538 | J12: 18538 | K12: 8528 | L12: 8528 | M12: Chris
A13: 2018 | B13: 3 | C13: Kelly Group | D13: NASL11 | E13: Order11 | F13: 74000254 | G13: 260 | H13: 52000 | I13: 36400 | J13: 36400 | K13: 15600 | L13: 15600 | M13: Vincent
A14: 2018 | B14: 3 | C14: Kelly Group | D14: NASL12 | E14: Order12 | F14: 88000426 | G14: 18 | H14: 68400 | I14: 0 | K14: 68400 | L14: 68400 | M14: Chris
A15: 2018 | B15: 3 | C15: Kelly Group | D15: NASL12 | E15: Order12 | F15: 88000426 | G15: 18 | H15: 68400 | I15: 26595.333 | J15: 26595.333 | K15: 41804.667 | L15: 41804.667 | M15: Chris
A16: 2018 | B16: 3 | C16: Kelly Group | D16: NASL12 | E16: Order13 | F16: 88000423 | G16: 17 | H16: 37400 | I16: 0 | K16: 37400 | L16: 37400 | M16: Chris
A17: 2018 | B17: 3 | C17: Kelly Group | D17: NASL12 | E17: Order13 | F17: 88000423 | G17: 17 | H17: 37400 | I17: 18687 | J17: 18687 | K17: 18713 | L17: 18713 | M17: Chris
A18: 2018 | B18: 3 | C18: Kelly Group | D18: NASL12 | E18: Order14 | F18: 87000085 | G18: 17 | H18: 30600 | I18: 0 | K18: 30600 | L18: 30600 | M18: Chris
A19: 2018 | B19: 3 | C19: Kelly Group | D19: NASL12 | E19: Order14 | F19: 87000085 | G19: 17 | H19: 30600 | I19: 21134 | J19: 21134 | K19: 9466 | L19: 9466 | M19: Chris
A20: 2018 | B20: 3 | C20: Kelly Group | D20: NASL12 | E20: Order15 | F20: 88000407 | G20: 34 | H20: 36550 | I20: 0 | K20: 36550 | L20: 36550 | M20: Chris
A21: 2018 | B21: 3 | C21: Kelly Group | D21: NASL12 | E21: Order15 | F21: 88000407 | G21: 34 | H21: 36550 | I21: 20094.182 | J21: 20094.182 | K21: 16455.818 | L21: 16455.818 | M21: Chris
A22: 2018 | B22: 3 | C22: Kelly Group | D22: NASL12 | E22: Order16 | F22: 88000426 | G22: 36 | H22: 118800 | I22: 0 | K22: 118800 | L22: 118800 | M22: Chris
A23: 2018 | B23: 3 | C23: Kelly Group | D23: NASL12 | E23: Order16 | F23: 88000426 | G23: 36 | H23: 118800 | I23: 53190.667 | J23: 53190.667 | K23: 65609.333 | L23: 65609.333 | M23: Chris
A24: 2018 | B24: 3 | C24: Kelly Group | D24: NASL12 | E24: Order17 | F24: 88000407 | G24: 153 | H24: 164475 | I24: 0 | K24: 164475 | L24: 164475 | M24: Chris
A25: 2018 | B25: 3 | C25: Kelly Group | D25: NASL12 | E25: Order17 | F25: 88000407 | G25: 153 | H25: 164475 | I25: 90423.818 | J25: 90423.818 | K25: 74051.182 | L25: 74051.182 | M25: Chris
A26: 2018 | B26: 3 | C26: Kelly Group | D26: NASL11 | E26: Order18 | F26: 61000027 | G26: 120 | H26: 21000 | I26: 4663.9999 | J26: 4663.9999 | K26: 16336 | L26: 16336 | M26: Ian
A27: 2018 | B27: 3 | C27: Kelly Group | D27: NASL11 | E27: Order19 | F27: 61000017 | G27: 300 | H27: 43500 | I27: 25265 | J27: 25265 | K27: 18235 | L27: 18235 | M27: Ian
A28: 2018 | B28: 3 | C28: Kelly Group | D28: NASL12 | E28: Order20 | F28: 88000411 | G28: 17 | H28: 79900 | I28: 0 | K28: 79900 | L28: 79900 | M28: Chris
A29: 2018 | B29: 3 | C29: Kelly Group | D29: NASL12 | E29: Order20 | F29: 88000411 | G29: 17 | H29: 79900 | I29: 32759 | J29: 32759 | K29: 47141 | L29: 47141 | M29: Chris
A30: 2018 | B30: 3 | C30: Kelly Group | D30: NASL12 | E30: Order21 | F30: 88000413 | G30: 19 | H30: 68400 | I30: 0 | K30: 68400 | L30: 68400 | M30: Chris
A31: 2018 | B31: 3 | C31: Kelly Group | D31: NASL12 | E31: Order21 | F31: 88000413 | G31: 19 | H31: 68400 | I31: 42109 | J31: 42109 | K31: 26291 | L31: 26291 | M31: Chris
A32: 2018 | B32: 3 | C32: Kelly Group | D32: NASL11 | E32: Order22 | F32: 74000245 | G32: 750 | H32: 187500 | I32: 114000 | J32: 114000 | K32: 73500 | L32: 73500 | M32: Vincent
A33: 2018 | B33: 3 | C33: Kelly Group | D33: NASL11 | E33: Order23 | F33: 74000245 | G33: 500 | H33: 125000 | I33: 76000 | J33: 76000 | K33: 49000 | L33: 49000 | M33: Vincent
A34: 2018 | B34: 3 | C34: Kelly Group | D34: NASL11 | E34: Order24 | F34: 74000071 | G34: 20 | H34: 4500 | I34: 2420.6667 | J34: 2420.6667 | K34: 2079.3333 | L34: 2079.3333 | M34: Vincent
A35: 2018 | B35: 3 | C35: Kelly Group | D35: NASL11 | E35: Order25 | F35: 74000071 | G35: 40 | H35: 9000 | I35: 4841.3333 | J35: 4841.3333 | K35: 4158.6667 | L35: 4158.6667 | M35: Vincent
A36: 2018 | B36: 3 | C36: Kelly Group | D36: NASL11 | E36: Order26 | F36: 74000252 | G36: 90 | H36: 38250 | I36: 27815 | J36: 27815 | K36: 10435 | L36: 10435 | M36: Vincent
A37: 2018 | B37: 3 | C37: Kelly Group | D37: NASL12 | E37: Order27 | F37: 88000428 | G37: 3 | H37: 24600 | I37: 0 | K37: 24600 | L37: 24600 | M37: Chris
A38: 2018 | B38: 3 | C38: Kelly Group | D38: NASL12 | E38: Order27 | F38: 88000428 | G38: 3 | H38: 24600 | I38: 9741 | J38: 9741 | K38: 14859 | L38: 14859 | M38: Chris
A39: 2018 | B39: 3 | C39: Kelly Group | D39: NASL12 | E39: Order28 | F39: 88000535 | G39: 16 | H39: 14400 | I39: 5896 | J39: 5896 | K39: 8504 | L39: 8504 | M39: Chris
A40: 2018 | B40: 3 | C40: Kelly Group | D40: NASL12 | E40: Order29 | F40: 88000554 | G40: 15 | H40: 12750 | I40: 6649 | J40: 6649 | K40: 6101 | L40: 6101 | M40: Chris
A41: 2018 | B41: 3 | C41: Kelly Group | D41: NASL12 | E41: Order30 | F41: 88000554 | G41: 15 | H41: 12750 | I41: 6649 | J41: 6649 | K41: 6101 | L41: 6101 | M41: Chris
A42: 2018 | B42: 3 | C42: Kelly Group | D42: NASL11 | E42: Order31 | F42: 61000028 | G42: 480 | H42: 76800 | I42: 15966 | J42: 15966 | K42: 60834 | L42: 60834 | M42: Ian
A43: 2018 | B43: 3 | C43: Kelly Group | D43: NASL12 | E43: Order32 | F43: 88000522 | G43: 16 | H43: 20480 | I43: 0 | K43: 20480 | L43: 20480 | M43: Chris
A44: 2018 | B44: 3 | C44: Kelly Group | D44: NASL12 | E44: Order32 | F44: 88000522 | G44: 16 | H44: 20480 | I44: 2222 | J44: 2222 | K44: 18258 | L44: 18258 | M44: Chris
A45: 2018 | B45: 3 | C45: Kelly Group | D45: NASL12 | E45: Order33 | F45: 61000027 | G45: 30 | H45: 5400 | I45: 1166 | J45: 1166 | K45: 4234 | L45: 4234 | M45: Chris
A46: 2018 | B46: 4 | C46: Kelly Group | D46: NASL12 | E46: Order34 | F46: 61000017 | G46: 20 | H46: 8000 | I46: 0 | K46: 8000 | L46: 8000 | M46: Louis
A47: 2018 | B47: 4 | C47: Kelly Group | D47: NASL12 | E47: Order34 | F47: 61000017 | G47: 20 | H47: 8000 | I47: 1658.7317 | J47: 1658.7317 | K47: 6341.2683 | L47: 6341.2683 | M47: Louis
A48: 2018 | B48: 4 | C48: Kelly Group | D48: NASL11 | E48: Order35 | F48: 74000254 | G48: 300 | H48: 60000 | I48: 42000 | J48: 42000 | K48: 18000 | L48: 18000 | M48: Vincent
A49: 2018 | B49: 4 | C49: Kelly Group | D49: NASL11 | E49: Order36 | F49: 74000162 | G49: 2500 | H49: 312500 | I49: 178673 | J49: 178673 | K49: 133827 | L49: 133827 | M49: Vincent
A50: 2018 | B50: 4 | C50: Kelly Group | D50: NASL12 | E50: Order37 | F50: 88000426 | G50: 36 | H50: 118800 | I50: 0 | K50: 118800 | L50: 118800 | M50: Chris
A51: 2018 | B51: 4 | C51: Kelly Group | D51: NASL12 | E51: Order37 | F51: 88000426 | G51: 36 | H51: 118800 | I51: 52380 | J51: 52380 | K51: 66420 | L51: 66420 | M51: Chris
A52: 2018 | B52: 4 | C52: Kelly Group | D52: NASL12 | E52: Order38 | F52: 88000426 | G52: 18 | H52: 68400 | I52: 0 | K52: 68400 | L52: 68400 | M52: Chris
A53: 2018 | B53: 4 | C53: Kelly Group | D53: NASL12 | E53: Order38 | F53: 88000426 | G53: 18 | H53: 68400 | I53: 26190 | J53: 26190 | K53: 42210 | L53: 42210 | M53: Chris
A54: 2018 | B54: 4 | C54: Kelly Group | D54: NASL12 | E54: Order39 | F54: 88000407 | G54: 476 | H54: 511700 | I54: 0 | K54: 511700 | L54: 511700 | M54: Chris
A55: 2018 | B55: 4 | C55: Kelly Group | D55: NASL12 | E55: Order39 | F55: 88000407 | G55: 476 | H55: 511700 | I55: 277034.9 | J55: 277034.9 | K55: 234665.1 | L55: 234665.1 | M55: Chris
A56: 2018 | B56: 4 | C56: Kelly Group | D56: NASL12 | E56: Order40 | F56: 88000535 | G56: 16 | H56: 14400 | I56: 0 | K56: 14400 | L56: 14400 | M56: Chris
A57: 2018 | B57: 4 | C57: Kelly Group | D57: NASL12 | E57: Order40 | F57: 88000535 | G57: 16 | H57: 14400 | I57: 5806 | J57: 5806 | K57: 8594 | L57: 8594 | M57: Chris
A58: 2018 | B58: 4 | C58: Kelly Group | D58: NASL12 | E58: Order41 | F58: 88000554 | G58: 15 | H58: 12750 | I58: 0 | K58: 12750 | L58: 12750 | M58: Chris
A59: 2018 | B59: 4 | C59: Kelly Group | D59: NASL12 | E59: Order41 | F59: 88000554 | G59: 15 | H59: 12750 | I59: 6548 | J59: 6548 | K59: 6202 | L59: 6202 | M59: Chris
A60: 2018 | B60: 4 | C60: Kelly Group | D60: NASL11 | E60: Order42 | F60: 61000027 | G60: 60 | H60: 9600 | I60: 0 | K60: 9600 | L60: 9600 | M60: Ian
A61: 2018 | B61: 4 | C61: Kelly Group | D61: NASL11 | E61: Order42 | F61: 61000027 | G61: 60 | H61: 9600 | I61: 2332 | J61: 2332 | K61: 7268 | L61: 7268 | M61: Ian
A62: 2018 | B62: 4 | C62: Kelly Group | D62: NASL12 | E62: Order43 | F62: 88000423 | G62: 34 | H62: 74800 | I62: 33640 | J62: 33640 | K62: 41160 | L62: 41160 | M62: Chris
A63: 2018 | B63: 4 | C63: Kelly Group | D63: NASL12 | E63: Order44 | F63: 88000409 | G63: 17 | H63: 42500 | I63: 22261.667 | J63: 22261.667 | K63: 20238.333 | L63: 20238.333 | M63: Chris
A64: 2018 | B64: 4 | C64: Kelly Group | D64: NASL12 | E64: Order45 | F64: 88000409 | G64: 51 | H64: 127500 | I64: 66785 | J64: 66785 | K64: 60715 | L64: 60715 | M64: Chris
A65: 2018 | B65: 4 | C65: Kelly Group | D65: NASL12 | E65: Order46 | F65: 87000060 | G65: 1 | H65: 28500 | I65: 0 | K65: 28500 | L65: 28500 | M65: Louis
A66: 2018 | B66: 4 | C66: Kelly Group | D66: NASL12 | E66: Order46 | F66: 87000060 | G66: 1 | H66: 28500 | I66: 16412 | J66: 16412 | K66: 12088 | L66: 12088 | M66: Louis
A67: 2018 | B67: 4 | C67: Kelly Group | D67: NASL12 | E67: Order47 | F67: 88000413 | G67: 19 | H67: 68400 | I67: 41468 | J67: 41468 | K67: 26932 | L67: 26932 | M67: Chris
A68: 2018 | B68: 4 | C68: Kelly Group | D68: NASL12 | E68: Order48 | F68: 88000418 | G68: 18 | H68: 72000 | I68: 42246 | J68: 42246 | K68: 29754 | L68: 29754 | M68: Chris
A69: 2018 | B69: 4 | C69: Kelly Group | D69: NASL11 | E69: Order49 | F69: 74000193 | G69: 415.6 | H69: 60000 | I69: 33664 | J69: 33664 | K69: 26336 | L69: 26336 | M69: Vincent
A70: 2018 | B70: 4 | C70: Kelly Group | D70: NASL12 | E70: Order50 | F70: 88000407 | G70: 17 | H70: 17442 | I70: 0 | K70: 17442 | L70: 17442 | M70: Chris
A71: 2018 | B71: 4 | C71: Kelly Group | D71: NASL12 | E71: Order50 | F71: 88000407 | G71: 17 | H71: 17442 | I71: 9894.1034 | J71: 9894.1034 | K71: 7547.8966 | L71: 7547.8966 | M71: Chris
A72: 2018 | B72: 4 | C72: Kelly Group | D72: NASL11 | E72: Order51 | F72: 74000158 | G72: 60 | H72: 10500 | I72: 6180.75 | J72: 6180.75 | K72: 4319.25 | L72: 4319.25 | M72: Vincent
A73: 2018 | B73: 4 | C73: Kelly Group | D73: NASL12 | E73: Order52 | F73: 87000189 | G73: 36 | H73: 15300 | I73: 0 | K73: 15300 | L73: 15300 | M73: Louis
A74: 2018 | B74: 4 | C74: Kelly Group | D74: NASL12 | E74: Order52 | F74: 87000189 | G74: 36 | H74: 15300 | I74: 7282 | J74: 7282 | K74: 8018 | L74: 8018 | M74: Louis
A75: 2018 | B75: 4 | C75: Kelly Group | D75: NASL11 | E75: Order53 | F75: 61000027 | G75: 120 | H75: 21000 | I75: 0 | K75: 21000 | L75: 21000 | M75: Ian
A76: 2018 | B76: 4 | C76: Kelly Group | D76: NASL11 | E76: Order53 | F76: 61000027 | G76: 120 | H76: 21000 | I76: 4663.9999 | J76: 4663.9999 | K76: 16336 | L76: 16336 | M76: Ian
A77: 2018 | B77: 4 | C77: Kelly Group | D77: NASL11 | E77: Order54 | F77: 61000017 | G77: 200 | H77: 29000 | I77: 0 | K77: 29000 | L77: 29000 | M77: Ian
A78: 2018 | B78: 4 | C78: Kelly Group | D78: NASL11 | E78: Order54 | F78: 61000017 | G78: 200 | H78: 29000 | I78: 16587.317 | J78: 16587.317 | K78: 12412.683 | L78: 12412.683 | M78: Ian
A79: 2018 | B79: 4 | C79: Kelly Group | D79: NASL11 | E79: Order55 | F79: 74000158 | G79: 20 | H79: 3500 | I79: 2060.25 | J79: 2060.25 | K79: 1439.75 | L79: 1439.75 | M79: Vincent
A80: 2018 | B80: 4 | C80: Kelly Group | D80: NASL11 | E80: Order56 | F80: 74000150 | G80: 40 | H80: 6800 | I80: 3850 | J80: 3850 | K80: 2950 | L80: 2950 | M80: Vincent
A81: 2018 | B81: 4 | C81: Kelly Group | D81: NASL11 | E81: Order57 | F81: 61000017 | G81: 300 | H81: 66900 | I81: 0 | K81: 66900 | L81: 66900 | M81: Ian
A82: 2018 | B82: 4 | C82: Kelly Group | D82: NASL11 | E82: Order57 | F82: 61000017 | G82: 300 | H82: 66900 | I82: 24880.976 | J82: 24880.976 | K82: 42019.024 | L82: 42019.024 | M82: Ian
A83: 2018 | B83: 4 | C83: Kelly Group | D83: NASL12 | E83: Order58 | F83: 88000435 | G83: 85 | H83: 245650 | I83: 103888 | J83: 103888 | K83: 141762 | L83: 141762 | M83: Chris
A84: 2018 | B84: 4 | C84: Kelly Group | D84: NASL12 | E84: Order59 | F84: 88000409 | G84: 34 | H84: 85000 | I84: 44523.333 | J84: 44523.333 | K84: 40476.667 | L84: 40476.667 | M84: Chris
A85: 2018 | B85: 4 | C85: Kelly Group | D85: NASL11 | E85: Order60 | F85: 74000071 | G85: 20 | H85: 5000 | I85: 2383 | J85: 2383 | K85: 2617 | L85: 2617 | M85: Vincent
A86: 2018 | B86: 4 | C86: Kelly Group | D86: NASL11 | E86: Order61 | F86: 74000253 | G86: 175 | H86: 21875 | I86: 16492 | J86: 16492 | K86: 5383 | L86: 5383 | M86: Vincent
A87: 2018 | B87: 4 | C87: Kelly Group | D87: NASL11 | E87: Order62 | F87: 71000576 | G87: 20 | H87: 6400 | I87: 2597 | J87: 2597 | K87: 3803 | L87: 3803 | M87: Vincent
A88: 2018 | B88: 4 | C88: Kelly Group | D88: NASL11 | E88: Order63 | F88: 74000246 | G88: 232.4 | H88: 46480 | I88: 0 | K88: 46480 | L88: 46480 | M88: Ian
A89: 2018 | B89: 4 | C89: Kelly Group | D89: NASL11 | E89: Order63 | F89: 74000246 | G89: 232.4 | H89: 46480 | I89: 12550 | J89: 12550 | K89: 33930 | L89: 33930 | M89: Ian
A90: 2018 | B90: 4 | C90: Kelly Group | D90: NASL11 | E90: Order64 | F90: 72000045 | G90: 19.7 | H90: 4925 | I90: 0 | K90: 4925 | L90: 4925 | M90: Ian
A91: 2018 | B91: 4 | C91: Kelly Group | D91: NASL11 | E91: Order64 | F91: 72000045 | G91: 19.7 | H91: 4925 | I91: 1286 | J91: 1286 | K91: 3639 | L91: 3639 | M91: Ian
A92: 2018 | B92: 4 | C92: Kelly Group | D92: NASL11 | E92: Order65 | F92: 61000027 | G92: 120 | H92: 21000 | I92: 0 | K92: 21000 | L92: 21000 | M92: Ian
A93: 2018 | B93: 4 | C93: Kelly Group | D93: NASL11 | E93: Order65 | F93: 61000027 | G93: 120 | H93: 21000 | I93: 4663.9999 | J93: 4663.9999 | K93: 16336 | L93: 16336 | M93: Ian
A94: 2018 | B94: 4 | C94: Kelly Group | D94: NASL11 | E94: Order66 | F94: 61000017 | G94: 300 | H94: 43500 | I94: 0 | K94: 43500 | L94: 43500 | M94: Ian
A95: 2018 | B95: 4 | C95: Kelly Group | D95: NASL11 | E95: Order66 | F95: 61000017 | G95: 300 | H95: 43500 | I95: 24880.976 | J95: 24880.976 | K95: 18619.024 | L95: 18619.024 | M95: Ian
A96: 2018 | B96: 4 | C96: Kelly Group | D96: NASL12 | E96: Order67 | F96: 74000251 | G96: 108 | H96: 247320 | I96: 0 | K96: 247320 | L96: 247320 | M96: Chris
A97: 2018 | B97: 4 | C97: Kelly Group | D97: NASL12 | E97: Order67 | F97: 74000251 | G97: 108 | H97: 247320 | I97: 220945 | J97: 220945 | K97: 26375 | L97: 26375 | M97: Chris
A98: 2018 | B98: 5 | C98: Kelly Group | D98: NASL11 | E98: Order100 | F98: 74000158 | G98: 214 | H98: 37450 | I98: 22045 | J98: 22045 | K98: 15405 | L98: 15405 | M98: Vincent
A99: 2018 | B99: 5 | C99: Kelly Group | D99: NASL11 | E99: Order101 | F99: 74000253 | G99: 175 | H99: 21875 | I99: 17307 | J99: 17307 | K99: 4568.0001 | L99: 4568.0001 | M99: Vincent
A100: 2018 | B100: 5 | C100: Kelly Group | D100: NASL11 | E100: Order102 | F100: 74000188 | G100: 580.8 | H100: 78408 | I100: 62731.999 | J100: 62731.999 | K100: 15676.001 | L100: 15676.001 | M100: Vincent
...

Sheet CustomerProfitResult
A1: 年 | B1: 月份 | C1: 期間資料版本 | D1: 公司 | E1: 事業單位 | F1: 顧客代碼 | G1: 顧客 | H1: 銷貨收入 | I1: 製造成本 | J1: 銷貨毛利 | K1: 銷貨作業成本 | L1: 資源直歸客戶成本 | M1: 總銷貨成本 | N1: 客戶利潤 | O1: 客戶利潤率
A2: 2018 | B2: 3 | C2: 201803 | D2: Kelly Group | E2: 公隆化學股份有限公司 | F2: CRM00024 | G2: 亞洲光學 | H2: 16000 | I2: 7229 | J2: 8771 | K2: 0 | L2: 0 | M2: 7229 | N2: 8771 | O2: 0.548187
A3: 2018 | B3: 3 | C3: 201803 | D3: Kelly Group | E3: 公隆化學股份有限公司 | F3: CRM00400 | G3: 東隆五金 | H3: 125000 | I3: 71469 | J3: 53531 | K3: 0 | L3: 0 | M3: 71469 | N3: 53531 | O3: 0.428248
A4: 2018 | B4: 3 | C4: 201803 | D4: Kelly Group | E4: 公隆化學股份有限公司 | F4: CRM00432 | G4: 佳能 | H4: 16200 | I4: 13292 | J4: 2908 | K4: 0 | L4: 0 | M4: 13292 | N4: 2908 | O4: 0.179506
A5: 2018 | B5: 3 | C5: 201803 | D5: Kelly Group | E5: 公隆化學股份有限公司 | F5: CRM00478 | G5: 億豐(代買士林電機) | H5: 38250 | I5: 27815 | J5: 10435 | K5: 0 | L5: 0 | M5: 27815 | N5: 10435 | O5: 0.27281
A6: 2018 | B6: 3 | C6: 201803 | D6: Kelly Group | E6: 公隆化學股份有限公司 | F6: CRM00696 | G6: 健達生物 | H6: 52000 | I6: 36400 | J6: 15600 | K6: 0 | L6: 0 | M6: 36400 | N6: 15600 | O6: 0.3
A7: 2018 | B7: 3 | C7: 201803 | D7: Kelly Group | E7: 公隆化學股份有限公司 | F7: CRM00860 | G7: 茂順 | H7: 60000 | I7: 33664 | J7: 26336 | K7: 0 | L7: 0 | M7: 33664 | N7: 26336 | O7: 0.438933
A8: 2018 | B8: 3 | C8: 201803 | D8: Kelly Group | E8: 公隆化學股份有限公司 | F8: CRM00888 | G8: 中壢億達薄膜 | H8: 13500 | I8: 7262 | J8: 6238 | K8: 0 | L8: 0 | M8: 7262 | N8: 6238 | O8: 0.462074
A9: 2018 | B9: 3 | C9: 201803 | D9: Kelly Group | E9: 公隆化學股份有限公司 | F9: CRM00911 | G9: 台灣鉅邁 | H9: 74900 | I9: 44091 | J9: 30809 | K9: 0 | L9: 0 | M9: 44091 | N9: 30809 | O9: 0.411335
A10: 2018 | B10: 3 | C10: 201803 | D10: Kelly Group | E10: 公隆化學股份有限公司 | F10: CRM00933 | G10: 榮助 | H10: 312500 | I10: 190000 | J10: 122500 | K10: 0 | L10: 0 | M10: 190000 | N10: 122500 | O10: 0.392
A11: 2018 | B11: 3 | C11: 201803 | D11: Kelly Group | E11: 公隆化學股份有限公司 | F11: CRM01025 | G11: 典雅實業 | H11: 76800 | I11: 15966 | J11: 60834 | K11: 0 | L11: 0 | M11: 15966 | N11: 60834 | O11: 0.792109
A12: 2018 | B12: 3 | C12: 201803 | D12: Kelly Group | E12: 公隆化學股份有限公司 | F12: CRM05197 | G12: 聯致科技 | H12: 39900 | I12: 19194 | J12: 20706 | K12: 0 | L12: 0 | M12: 19194 | N12: 20706 | O12: 0.518947
A13: 2018 | B13: 3 | C13: 201803 | D13: Kelly Group | E13: 公隆化學股份有限公司 | F13: CRM05498 | G13: 興勤電子 | H13: 24600 | I13: 9741 | J13: 14859 | K13: 0 | L13: 0 | M13: 9741 | N13: 14859 | O13: 0.604024
... A66: 2018 | B66: 5 | C66: 201805 | D66: Kelly Group | E66: 公隆化學股份有限公司 | F66: 華震科技 | G66: 華震科技 | H66: 122250 | I66: 44489.617 | J66: 77760.383 | K66: 0 | L66: 0 | M66: 44489.617 | N66: 77760.383 | O66: 0.636076

Sheet ProductProfitResult
A1: 年 | B1: 月份 | C1: 期間資料版本 | D1: 公司 | E1: 事業單位 | F1: 產品代碼 | G1: 產品 | H1: 銷售數量 | I1: 銷貨收入 | J1: 製造成本 | K1: 平均銷貨單價 | L1: 銷貨毛利 | M1: 銷貨作業成本 | N1: 資源直歸客戶成本 | O1: 專案成本(Project) | P1: 總銷貨成本 | Q1: 平均產品單位成本 | R1: 產品利潤 | S1: 產品利潤率
A2: 2018 | B2: 3 | C2: 201803 | D2: Kelly Group | E2: 公隆化學股份有限公司 | F2: 61000017 | G2: 絮凝劑 Neosorb GS-AN | H2: 300 | I2: 43500 | J2: 25265 | K2: 145 | L2: 18235 | M2: 0 | N2: 0 | O2: 0 | P2: 25265 | Q2: 84.216666 | R2: 18235 | S2: 0.419195
A3: 2018 | B3: 3 | C3: 201803 | D3: Kelly Group | E3: 公隆化學股份有限公司 | F3: 61000027 | G3: 重金屬捕集劑 Plexon 3315 30KG/CAN | H3: 150 | I3: 26400 | J3: 5829.9999 | K3: 176 | L3: 20570 | M3: 0 | N3: 0 | O3: 0 | P3: 5829.9999 | Q3: 38.866666 | R3: 20570 | S3: 0.779166
A4: 2018 | B4: 3 | C4: 201803 | D4: Kelly Group | E4: 公隆化學股份有限公司 | F4: 61000028 | G4: 重金屬捕集劑 Plexon 3315(D | H4: 480 | I4: 76800 | J4: 15966 | K4: 160 | L4: 60834 | M4: 0 | N4: 0 | O4: 0 | P4: 15966 | Q4: 33.2625 | R4: 60834 | S4: 0.792109
A5: 2018 | B5: 3 | C5: 201803 | D5: Kelly Group | E5: 公隆化學股份有限公司 | F5: 71000576 | G5: CS-718 鏡片清洗劑 20KG/PAL (JP | H5: 20 | I5: 6400 | J5: 2637 | K5: 320 | L5: 3763 | M5: 0 | N5: 0 | O5: 0 | P5: 2637 | Q5: 131.85 | R5: 3763 | S5: 0.587968
A6: 2018 | B6: 3 | C6: 201803 | D6: Kelly Group | E6: 公隆化學股份有限公司 | F6: 74000063 | G6: CE CLEANER 550 (20KG/BAG,CN | H6: 20 | I6: 9600 | J6: 4592 | K6: 480 | L6: 5008 | M6: 0 | N6: 0 | O6: 0 | P6: 4592 | Q6: 229.6 | R6: 5008 | S6: 0.521666
A7: 2018 | B7: 3 | C7: 201803 | D7: Kelly Group | E7: 公隆化學股份有限公司 | F7: 74000071 | G7: CE REMOVER 810 (20KG/PAL,CN | H7: 60 | I7: 13500 | J7: 7262 | K7: 225 | L7: 6238 | M7: 0 | N7: 0 | O7: 0 | P7: 7262 | Q7: 121.03333 | R7: 6238 | S7: 0.462074
A8: 2018 | B8: 3 | C8: 201803 | D8: Kelly Group | E8: 公隆化學股份有限公司 | F8: 74000158 | G8: CONTROX E162 214KG/DRUM | H8: 428 | I8: 74900 | J8: 44091 | K8: 175 | L8: 30809 | M8: 0 | N8: 0 | O8: 0 | P8: 44091 | Q8: 103.01636 | R8: 30809 | S8: 0.411335
A9: 2018 | B9: 3 | C9: 201803 | D9: Kelly Group | E9: 公隆化學股份有限公司 | F9: 74000162 | G9: CONTROX E230 250KG/DRUM | H9: 1000 | I9: 125000 | J9: 71469 | K9: 125 | L9: 53531 | M9: 0 | N9: 0 | O9: 0 | P9: 71469 | Q9: 71.469 | R9: 53531 | S9: 0.428248
A10: 2018 | B10: 3 | C10: 201803 | D10: Kelly Group | E10: 公隆化學股份有限公司 | F10: 74000193 | G10: HAKUFORM A 801 207.8KG/DRUM | H10: 415.6 | I10: 60000 | J10: 33664 | K10: 144.36959 | L10: 26336 | M10: 0 | N10: 0 | O10: 0 | P10: 33664 | Q10: 81.000961 | R10: 26336 | S10: 0.438933
A11: 2018 | B11: 3 | C11: 201803 | D11: Kelly Group | E11: 公隆化學股份有限公司 | F11: 74000242 | G11: CS CLEAN 18KG/PAIL | H11: 36 | I11: 16200 | J11: 13292 | K11: 450 | L11: 2908 | M11: 0 | N11: 0 | O11: 0 | P11: 13292 | Q11: 369.22222 | R11: 2908 | S11: 0.179506
A12: 2018 | B12: 3 | C12: 201803 | D12: Kelly Group | E12: 公隆化學股份有限公司 | F12: 74000245 | G12: CONTROX B42 25KG/PAIL | H12: 1250 | I12: 312500 | J12: 190000 | K12: 250 | L12: 122500 | M12: 0 | N12: 0 | O12: 0 | P12: 190000 | Q12: 152 | R12: 122500 | S12: 0.392
A13: 2018 | B13: 3 | C13: 201803 | D13: Kelly Group | E13: 公隆化學股份有限公司 | F13: 74000252 | G13: CHEMISOL 2504 18KG/PAIL | H13: 90 | I13: 38250 | J13: 27815 | K13: 425 | L13: 10435 | M13: 0 | N13: 0 | O13: 0 | P13: 27815 | Q13: 309.05556 | R13: 10435 | S13: 0.27281
... A80: 2018 | B80: 5 | C80: 201805 | D80: Kelly Group | E80: 公隆化學股份有限公司 | F80: 88100060 | G80: 催化剂 K-PURE CXC-1612 1LB/PACKAGE | H80: 5 | I80: 104330 | J80: 60449 | K80: 20866 | L80: 43881 | M80: 0 | N80: 0 | O80: 4568.7366 | P80: 65017.737 | Q80: 13003.547 | R80: 39312.263 | S80: 0.376806

Sheet CustomerProductProfit
A1: 年 | B1: 月份 | C1: 期間資料版本 | D1: 公司 | E1: 事業單位代碼 | F1: 顧客 | G1: 訂單編號 | H1: 銷售作業中心 | I1: 出貨事業單位 | J1: 產品 | K1: 銷貨收入 | L1: 產品成本庫 | M1: 毛利率 | N1: 產品管理成本(Management) | O1: 客戶服務成本(Service) | P1: 專案成本(Project) | Q1: 總銷貨成本 | R1: 淨利 | S1: 數量 | T1: 淨利率 | U1: 業務工程師
A2: 2018 | B2: 3 | C2: 201803 | D2: Kelly Group | E2: 公隆化學股份有限公司:公隆化學股份有限公司 | F2: CRM08406:永光化學 | G2: Order01 | H2: NASL12:電子化學課 | I2: 公隆化學股份有限公司:公隆化學股份有限公司 | J2: 87000189:UV樹酯 ART RESIN UN-981 18KG/PAIL | K2: 30600 | L2: 14564 | M2: 16036 | N2: 0 | O2: 0 | P2: 0 | Q2: 14564 | R2: 16036 | S2: 72 | T2: 0.524052 | U2: Louis
A3: 2018 | B3: 3 | C3: 201803 | D3: Kelly Group | E3: 公隆化學股份有限公司:公隆化學股份有限公司 | F3: CRM00432:佳能 | G3: Order02 | H3: NASL11:製程化學課 | I3: 公隆化學股份有限公司:公隆化學股份有限公司 | J3: 74000242:CS CLEAN 18KG/PAIL | K3: 16200 | L3: 13292 | M3: 2908 | N3: 0 | O3: 0 | P3: 0 | Q3: 13292 | R3: 2908 | S3: 36 | T3: 0.179506 | U3: Vincent
A4: 2018 | B4: 3 | C4: 201803 | D4: Kelly Group | E4: 公隆化學股份有限公司:公隆化學股份有限公司 | F4: CRM00911:台灣鉅邁 | G4: Order03 | H4: NASL11:製程化學課 | I4: 公隆化學股份有限公司:公隆化學股份有限公司 | J4: 74000158:CONTROX E162 214KG/DRUM | K4: 74900 | L4: 44091 | M4: 30809 | N4: 0 | O4: 0 | P4: 0 | Q4: 44091 | R4: 30809 | S4: 428 | T4: 0.411335 | U4: Vincent
A5: 2018 | B5: 3 | C5: 201803 | D5: Kelly Group | E5: 公隆化學股份有限公司:公隆化學股份有限公司 | F5: CRM00024:亞洲光學 | G5: Order04 | H5: NASL11:製程化學課 | I5: 公隆化學股份有限公司:公隆化學股份有限公司 | J5: 74000063:CE CLEANER 550 (20KG/BAG,CN | K5: 9600 | L5: 4592 | M5: 5008 | N5: 0 | O5: 0 | P5: 0 | Q5: 4592 | R5: 5008 | S5: 20 | T5: 0.521666 | U5: Vincent
A6: 2018 | B6: 3 | C6: 201803 | D6: Kelly Group | E6: 公隆化學股份有限公司:公隆化學股份有限公司 | F6: CRM00024:亞洲光學 | G6: Order05 | H6: NASL11:製程化學課 | I6: 公隆化學股份有限公司:公隆化學股份有限公司 | J6: 71000576:CS-718 鏡片清洗劑 20KG/PAL (JP | K6: 6400 | L6: 2637 | M6: 3763 | N6: 0 | O6: 0 | P6: 0 | Q6: 2637 | R6: 3763 | S6: 20 | T6: 0.587968 | U6: Vincent
A7: 2018 | B7: 3 | C7: 201803 | D7: Kelly Group | E7: 公隆化學股份有限公司:公隆化學股份有限公司 | F7: CRM00400:東隆五金 | G7: Order06 | H7: NASL11:製程化學課 | I7: 公隆化學股份有限公司:公隆化學股份有限公司 | J7: 74000162:CONTROX E230 250KG/DRUM | K7: 125000 | L7: 71469 | M7: 53531 | N7: 0 | O7: 0 | P7: 0 | Q7: 71469 | R7: 53531 | S7: 1000 | T7: 0.428248 | U7: Vincent
A8: 2018 | B8: 3 | C8: 201803 | D8: Kelly Group | E8: 公隆化學股份有限公司:公隆化學股份有限公司 | F8: CRM17296:台灣美磊 | G8: Order07 | H8: NASL12:電子化學課 | I8: 公隆化學股份有限公司:公隆化學股份有限公司 | J8: 88000513:觸變劑 DISPARLON BB-102 16KG/PAIL | K8: 15360 | L8: 5248 | M8: 10112 | N8: 0 | O8: 0 | P8: 1536.2271 | Q8: 6784.2271 | R8: 8575.7729 | S8: 16 | T8: 0.558318 | U8: Chris
A9: 2018 | B9: 3 | C9: 201803 | D9: Kelly Group | E9: 公隆化學股份有限公司:公隆化學股份有限公司 | F9: CRM00860:茂順 | G9: Order08 | H9: NASL11:製程化學課 | I9: 公隆化學股份有限公司:公隆化學股份有限公司 | J9: 74000193:HAKUFORM A 801 207.8KG/DRUM | K9: 60000 | L9: 33664 | M9: 26336 | N9: 0 | O9: 0 | P9: 0 | Q9: 33664 | R9: 26336 | S9: 415.6 | T9: 0.438933 | U9: Vincent
A10: 2018 | B10: 3 | C10: 201803 | D10: Kelly Group | E10: 公隆化學股份有限公司:公隆化學股份有限公司 | F10: CRM17381:桃園-愛賽克 | G10: Order09 | H10: NASL12:電子化學課 | I10: 公隆化學股份有限公司:公隆化學股份有限公司 | J10: 87000182:UV樹脂 ART RESIN UN-9200A 15KG/PAIL | K10: 60210 | L10: 40292 | M10: 19918 | N10: 0 | O10: 0 | P10: 0 | Q10: 40292 | R10: 19918 | S10: 45 | T10: 0.330808 | U10: Chris
A11: 2018 | B11: 3 | C11: 201803 | D11: Kelly Group | E11: 公隆化學股份有限公司:公隆化學股份有限公司 | F11: CRM17381:桃園-愛賽克 | G11: Order10 | H11: NASL12:電子化學課 | I11: 公隆化學股份有限公司:公隆化學股份有限公司 | J11: 87000175:UV樹脂 ART RESIN UN-6060PTM 13KG/PAIL (Zn | K11: 27066 | L11: 18538 | M11: 8528 | N11: 0 | O11: 0 | P11: 0 | Q11: 18538 | R11: 8528 | S11: 26 | T11: 0.315081 | U11: Chris
A12: 2018 | B12: 3 | C12: 201803 | D12: Kelly Group | E12: 公隆化學股份有限公司:公隆化學股份有限公司 | F12: CRM00696:健達生物 | G12: Order11 | H12: NASL11:製程化學課 | I12: 公隆化學股份有限公司:公隆化學股份有限公司 | J12: 74000254:CE800塗料剝離劑 20KG/PAIL (TW | K12: 52000 | L12: 36400 | M12: 15600 | N12: 0 | O12: 0 | P12: 0 | Q12: 36400 | R12: 15600 | S12: 260 | T12: 0.3 | U12: Vincent
A13: 2018 | B13: 3 | C13: 201803 | D13: Kelly Group | E13: 公隆化學股份有限公司:公隆化學股份有限公司 | F13: CRM11533:國巨楠梓 | G13: Order12 | H13: NASL12:電子化學課 | I13: 公隆化學股份有限公司:公隆化學股份有限公司 | J13: 88000426:分散劑 HIPLAAD ED400 18KG/PAIL | K13: 68400 | L13: 26595.333 | M13: 41804.667 | N13: 0 | O13: 0 | P13: 8637.8723 | Q13: 35233.206 | R13: 33166.794 | S13: 18 | T13: 0.484894 | U13: Chris
... A105: 2018 | B105: 5 | C105: 201805 | D105: Kelly Group | E105: 公隆化學股份有限公司:公隆化學股份有限公司 | F105: CRM11533:國巨楠梓 | G105: Order99 | H105: NASL12:電子化學課 | I105: 公隆化學股份有限公司:公隆化學股份有限公司 | J105: 88000435:分散劑 HIPLAAD SAD01 17KG/PAIL | K105: 245650 | L105: 110997 | M105: 134653 | N105: 0 | O105: 0 | P105: 0 | Q105: 110997 | R105: 134653 | S105: 85 | T105: 0.548149 | U105: Chris

Sheet 客戶利潤3-5
A1: 月份 | B1: (All)
A3: Row Labels | B3: 加總 - 銷貨收入 | C3: 加總 - 產品成本庫 | D3: 加總 - 毛利率 | E3: 加總 - 專案成本(Project) | F3: 加總 - 總銷貨成本 | G3: 加總 - 淨利 | J3: 淨利率
A4: 華震科技:華震科技 | B4: 301250 | C4: 125214.91 | D4: 176035.09 | E4: 50156.13 | F4: 175371.04 | G4: 125878.96 | J4: =GETPIVOTDATA("加總 - 淨利",$A$3,"顧客","華震科技:華震科技")/GETPIVOTDATA("加總 - 銷貨收入",$A$3,"顧客","華震科技:華震科技") -> 0.41785547
A5: CRM20308:九怡工業 | B5: 8000 | C5: 1658.7317 | D5: 6341.2683 | E5: 38156.137 | F5: 39814.869 | G5: -31814.869 | J5: =GETPIVOTDATA("加總 - 淨利",$A$3,"顧客","CRM20308:九怡工業")/GETPIVOTDATA("加總 - 銷貨收入",$A$3,"顧客","CRM20308:九怡工業") -> -3.9768586
A6: CRM10848:華新科技 | B6: 1099725 | C6: 569370.23 | D6: 530354.77 | E6: 14084.124 | F6: 583454.35 | G6: 516270.65 | J6: =GETPIVOTDATA("加總 - 淨利",$A$3,"顧客","華震科技:華震科技")/B6 -> 0.11446403
A7: CRM11533:國巨楠梓 | B7: 1266000 | C7: 587154.67 | D7: 678845.33 | E7: 13360.92 | F7: 600515.59 | G7: 665484.41 | J7: =GETPIVOTDATA("加總 - 淨利",$A$3,"顧客","華震科技:華震科技")/B7 -> 0.099430459
A8: CRM19822:友達 | B8: 247320 | C8: 220945 | D8: 26375 | E8: 9000.1455 | F8: 229945.15 | G8: 17374.855 | J8: =GETPIVOTDATA("加總 - 淨利",$A$3,"顧客","華震科技:華震科技")/B8 -> 0.50897202
A9: CRM16719:永源 | B9: 20480 | C9: 2222 | D9: 18258 | E9: 8910.117 | F9: 11132.117 | G9: 9347.883 | J9: =GETPIVOTDATA("加總 - 淨利",$A$3,"顧客","華震科技:華震科技")/B9 -> 6.1464336
A10: CRM01053:渼豐表面處理 | B10: 19200 | C10: 4741.8823 | D10: 14458.118 | E10: 7602.7282 | F10: 12344.611 | G10: 6855.3895 | J10: =GETPIVOTDATA("加總 - 淨利",$A$3,"顧客","華震科技:華震科技")/B10 -> 6.5561959
A11: CRM08411:新應材 | B11: 131330 | C11: 78218 | D11: 53112 | E11: 5751.0992 | F11: 83969.099 | G11: 47360.901 | J11: =GETPIVOTDATA("加總 - 淨利",$A$3,"顧客","華震科技:華震科技")/B11 -> 0.95849357
A12: CRM05498:興勤電子 | B12: 24600 | C12: 9741 | D12: 14859 | E12: 5643.6812 | F12: 15384.681 | G12: 9215.3188 | J12: =GETPIVOTDATA("加總 - 淨利",$A$3,"顧客","華震科技:華震科技")/B12 -> 5.1170309
A13: CRM08397:奇美實業 | B13: 30240 | C13: 21282 | D13: 8958 | E13: 5454.9956 | F13: 26736.996 | G13: 3503.0044 | J13: =GETPIVOTDATA("加總 - 淨利",$A$3,"顧客","華震科技:華震科技")/B13 -> 4.162664
A14: CRM01052:福懋科技 | B14: 133800 | C14: 51296.475 | D14: 82503.525 | E14: 5384.0752 | F14: 56680.55 | G14: 77119.45 | J14: =GETPIVOTDATA("加總 - 淨利",$A$3,"顧客","華震科技:華震科技")/B14 -> 0.94079941
A15: CRM00550:瑞興發 | B15: 9600 | C15: 7523.1786 | D15: 2076.8214 | E15: 4768.9803 | F15: 12292.159 | G15: -2692.1589 | J15: =GETPIVOTDATA("加總 - 淨利",$A$3,"顧客","華震科技:華震科技")/B15 -> 13.112392
A16: CRM08406:永光化學 | B16: 45900 | C16: 21846 | D16: 24054 | E16: 4698.0409 | F16: 26544.041 | G16: 19355.959 | J16: =GETPIVOTDATA("加總 - 淨利",$A$3,"顧客","華震科技:華震科技")/B16 -> 2.742461
A17: CRM10849:達方電子 | B17: 52326 | C17: 31068.103 | D17: 21257.897 | E17: 3577.6409 | F17: 34645.744 | G17: 17680.256 | J17: =GETPIVOTDATA("加總 - 淨利",$A$3,"顧客","華震科技:華震科技")/B17 -> 2.4056676
... A42: Grand Total | B42: 6208801 | C42: 3424293 | D42: 2784508 | E42: 186768.42 | F42: 3611061.4 | G42: 2597739.6 | J42: =GETPIVOTDATA("加總 - 淨利",$A$3,"顧客","華震科技:華震科技")/B42 -> 0.020274279

Sheet 產品利潤3-5
A1: 月份 | B1: (All)
A3: Row Labels | B3: 加總 - 銷貨收入 | C3: 加總 - 產品成本庫 | D3: 加總 - 毛利率 | E3: 加總 - 專案成本(Project) | F3: 加總 - 總銷貨成本 | G3: 加總 - 淨利 | J3: 淨利率
A4: 61000017:絮凝劑 Neosorb GS-AN | B4: 301300 | C4: 146104 | D4: 155196 | E4: 71824.712 | F4: 217928.71 | G4: 83371.289 | J4: =I4/B4 -> 0
A5: 61000027:重金屬捕集劑 Plexon 3315 30KG/CAN | B5: 166350 | C5: 37973.999 | D5: 128376 | E5: 29474.359 | F5: 67448.358 | G5: 98901.642 | J5: =I5/B5 -> 0
A6: 61000028:重金屬捕集劑 Plexon 3315(D | B6: 153600 | C6: 30654 | D6: 122946 | E6: 0 | F6: 30654 | G6: 122946 | J6: =I6/B6 -> 0
A7: 71000576:CS-718 鏡片清洗劑 20KG/PAL (JP | B7: 19200 | C7: 9231 | D7: 9969 | E7: 0 | F7: 9231 | G7: 9969 | J7: =I7/B7 -> 0
A8: 72000019:GX PROOF 6151 (20KG/PAL,CN | B8: 15400 | C8: 14393 | D8: 1007 | E8: 1987.0751 | F8: 16380.075 | G8: -980.07513 | J8: =I8/B8 -> 0
A9: 72000045:CUSTOS 625 25KG/PAIL | B9: 4925 | C9: 1286 | D9: 3639 | E9: 218.38329 | F9: 1504.3833 | G9: 3420.6167 | J9: =I9/B9 -> 0
A10: 72100012:產品72100012 | B10: 26434 | C10: 32008 | D10: -5574 | E10: 0 | F10: 32008 | G10: -5574 | J10: =I10/B10 -> 0
A11: 72100014:產品72100014 | B11: 50880 | C11: 54949 | D11: -4068.9998 | E11: 2781.9052 | F11: 57730.905 | G11: -6850.905 | J11: =I11/B11 -> 0
A12: 74000063:CE CLEANER 550 (20KG/BAG,CN | B12: 9600 | C12: 4592 | D12: 5008 | E12: 0 | F12: 4592 | G12: 5008 | J12: =I12/B12 -> 0
A13: 74000071:CE REMOVER 810 (20KG/PAL,CN | B13: 18500 | C13: 9645 | D13: 8855 | E13: 0 | F13: 9645 | G13: 8855 | J13: =I13/B13 -> 0
A14: 74000150:CONTROX 5042 16KG/PAIL | B14: 6800 | C14: 3850 | D14: 2950 | E14: 0 | F14: 3850 | G14: 2950 | J14: =I14/B14 -> 0
A15: 74000158:CONTROX E162 214KG/DRUM | B15: 126350 | C15: 74377 | D15: 51973 | E15: 0 | F15: 74377 | G15: 51973 | J15: =I15/B15 -> 0
... A50: Grand Total | B50: 6208801 | C50: 3424293 | D50: 2784508 | E50: 186768.42 | F50: 3611061.4 | G50: 2597739.6 | J50: =I50/B50 -> 0

Sheet 業務利潤3-5
A1: 月份 | B1: (全部)
A3: 列標籤 | B3: 加總 - 銷貨收入 | C3: 加總 - 總銷貨成本 | D3: 加總 - 淨利 | E3: 淨利率
A4: Chris | B4: 3567074 | C4: 2007884.9 | D4: 1559189.1 | E4: =D4/B4 -> 0.4371059
A5: CRM05197:聯致科技 | B5: 81450 | C5: 41866.636 | D5: 39583.364 | E5: =D5/B5 -> 0.48598359
A6: CRM05498:興勤電子 | B6: 24600 | C6: 15384.681 | D6: 9215.3188 | E6: =D6/B6 -> 0.37460646
A7: CRM08397:奇美實業 | B7: 30240 | C7: 26736.996 | D7: 3503.0044 | E7: =D7/B7 -> 0.11584009
A8: CRM08411:新應材 | B8: 131330 | C8: 83969.099 | D8: 47360.901 | E8: =D8/B8 -> 0.36062515
A9: CRM08704:肯美特 | B9: 30685 | C9: 20591 | D9: 10094 | E9: =D9/B9 -> 0.32895552
A10: CRM10771:勤凱-浚博 | B10: 315900 | C10: 177265.34 | D10: 138634.66 | E10: =D10/B10 -> 0.43885616
A11: CRM10848:華新科技 | B11: 1099725 | C11: 583454.35 | D11: 516270.65 | E11: =D11/B11 -> 0.46945431
A12: CRM10849:達方電子 | B12: 52326 | C12: 34645.744 | D12: 17680.256 | E12: =D12/B12 -> 0.33788663
A13: CRM11533:國巨楠梓 | B13: 1266000 | C13: 600515.59 | D13: 665484.41 | E13: =D13/B13 -> 0.52565909
A14: CRM16719:永源 | B14: 20480 | C14: 11132.117 | D14: 9347.883 | E14: =D14/B14 -> 0.4564396
A15: CRM17296:台灣美磊 | B15: 15360 | C15: 6784.2271 | D15: 8575.7729 | E15: =D15/B15 -> 0.55831855
... A47: 總計 | B47: 6208801 | C47: 3611061.4 | D47: 2597739.6 | E47: =D47/B47 -> 0.41839634
E48: =D48/B48 -> #DIV/0!
E49: =D49/B49 -> #DIV/0!
E50: =D50/B50 -> #DIV/0!
E51: =D51/B51 -> #DIV/0!
E52: =D52/B52 -> #DIV/0!
E53: =D53/B53 -> #DIV/0!
E54: =D54/B54 -> #DIV/0!
E55: =D55/B55 -> #DIV/0!
E56: =D56/B56 -> #DIV/0!
E57: =D57/B57 -> #DIV/0!
E58: =D58/B58 -> #DIV/0!
E59: =D59/B59 -> #DIV/0!
... E105: =D105/B105 -> #DIV/0!

Sheet InventoryResult
A1: 年 | B1: 月份 | C1: 期間資料版本 | D1: 公司 | E1: 事業單位 | F1: 料號代碼 | G1: 料號 | H1: 期初數量 | I1: 期初單價 | J1: 期初金額 | K1: 外購數量 | L1: 外購單價 | M1: 外購金額 | N1: 採購及製造成本 | O1: 當期生產單位成本 | P1: 可供銷售存貨數量 | Q1: 可供銷售存貨單價 | R1: 可供銷售存貨金額 | S1: 當期銷售數量 | T1: 當期銷售單價 | U1: 當期銷售金額 | V1: 期末存貨數量 | W1: 期末存貨單價 | X1: 期末存貨金額
A2: 2018 | B2: 3 | C2: 201803 | D2: Kelly Group | E2: 公隆化學股份有限公司 | F2: 88000535 | G2: 消泡劑 DISPARLON LAP-10 16KG/PAIL | H2: 0 | I2: 0 | J2: 0 | K2: 16 | L2: 368.5 | M2: 5896 | N2: 0 | O2: 368.5 | P2: 16 | Q2: 368.5 | R2: 5896 | S2: 16 | T2: 368.5 | U2: 5896 | V2: 0 | W2: 0 | X2: 0
A3: 2018 | B3: 3 | C3: 201803 | D3: Kelly Group | E3: 公隆化學股份有限公司 | F3: 88000413 | G3: 分散劑 HIPLAAD ED154 19KG/PAIL | H3: 0 | I3: 0 | J3: 0 | K3: 19 | L3: 2216.2632 | M3: 42109 | N3: 0 | O3: 2216.2632 | P3: 19 | Q3: 2216.2632 | R3: 42109 | S3: 19 | T3: 2216.2632 | U3: 42109 | V3: 0 | W3: 0 | X3: 0
A4: 2018 | B4: 3 | C4: 201803 | D4: Kelly Group | E4: 公隆化學股份有限公司 | F4: 74000245 | G4: CONTROX B42 25KG/PAIL | H4: 0 | I4: 0 | J4: 0 | K4: 1250 | L4: 152 | M4: 190000 | N4: 0 | O4: 152 | P4: 1250 | Q4: 152 | R4: 190000 | S4: 1250 | T4: 152 | U4: 190000 | V4: 0 | W4: 0 | X4: 0
A5: 2018 | B5: 3 | C5: 201803 | D5: Kelly Group | E5: 公隆化學股份有限公司 | F5: 74000158 | G5: CONTROX E162 214KG/DRUM | H5: 0 | I5: 0 | J5: 0 | K5: 428 | L5: 103.01636 | M5: 44091 | N5: 0 | O5: 103.01636 | P5: 428 | Q5: 103.01636 | R5: 44091 | S5: 428 | T5: 103.01636 | U5: 44091 | V5: 0 | W5: 0 | X5: 0
A6: 2018 | B6: 3 | C6: 201803 | D6: Kelly Group | E6: 公隆化學股份有限公司 | F6: 88000423 | G6: 分散劑 HIPLAAD ED251 17KG/PAIL | H6: 0 | I6: 0 | J6: 0 | K6: 17 | L6: 1099.2353 | M6: 18687 | N6: 0 | O6: 1099.2353 | P6: 17 | Q6: 1099.2353 | R6: 18687 | S6: 17 | T6: 1099.2353 | U6: 18687 | V6: 0 | W6: 0 | X6: 0
A7: 2018 | B7: 3 | C7: 201803 | D7: Kelly Group | E7: 公隆化學股份有限公司 | F7: 87000085 | G7: 樹脂 HIPLAAD ER 2300 17KG/PAIL | H7: 0 | I7: 0 | J7: 0 | K7: 17 | L7: 1243.1765 | M7: 21134 | N7: 0 | O7: 1243.1765 | P7: 17 | Q7: 1243.1765 | R7: 21134 | S7: 17 | T7: 1243.1765 | U7: 21134 | V7: 0 | W7: 0 | X7: 0
A8: 2018 | B8: 3 | C8: 201803 | D8: Kelly Group | E8: 公隆化學股份有限公司 | F8: 74000193 | G8: HAKUFORM A 801 207.8KG/DRUM | H8: 0 | I8: 0 | J8: 0 | K8: 415.6 | L8: 81.000962 | M8: 33664 | N8: 0 | O8: 81.000962 | P8: 415.6 | Q8: 81.000962 | R8: 33664 | S8: 415.6 | T8: 81.000962 | U8: 33664 | V8: 0 | W8: 0 | X8: 2e-06
A9: 2018 | B9: 3 | C9: 201803 | D9: Kelly Group | E9: 公隆化學股份有限公司 | F9: 88000554 | G9: 消泡劑 DISPARLON P-420 15KG/PAIL | H9: 0 | I9: 0 | J9: 0 | K9: 30 | L9: 443.26667 | M9: 13298 | N9: 0 | O9: 443.26667 | P9: 30 | Q9: 443.26667 | R9: 13298 | S9: 30 | T9: 443.26667 | U9: 13298 | V9: 0 | W9: 0 | X9: 0
A10: 2018 | B10: 3 | C10: 201803 | D10: Kelly Group | E10: 公隆化學股份有限公司 | F10: 88000428 | G10: 分散劑 HIPLAAD ED401 3KG/PAIL | H10: 0 | I10: 0 | J10: 0 | K10: 3 | L10: 3247 | M10: 9741 | N10: 0 | O10: 3247 | P10: 3 | Q10: 3247 | R10: 9741 | S10: 3 | T10: 3247 | U10: 9741 | V10: 0 | W10: 0 | X10: 0
A11: 2018 | B11: 3 | C11: 201803 | D11: Kelly Group | E11: 公隆化學股份有限公司 | F11: 87000175 | G11: UV樹脂 ART RESIN UN-6060PTM 13KG/PAIL (Zn | H11: 0 | I11: 0 | J11: 0 | K11: 26 | L11: 713 | M11: 18538 | N11: 0 | O11: 713 | P11: 26 | Q11: 713 | R11: 18538 | S11: 26 | T11: 713 | U11: 18538 | V11: 0 | W11: 0 | X11: 0
A12: 2018 | B12: 3 | C12: 201803 | D12: Kelly Group | E12: 公隆化學股份有限公司 | F12: 74000063 | G12: CE CLEANER 550 (20KG/BAG,CN | H12: 0 | I12: 0 | J12: 0 | K12: 20 | L12: 229.6 | M12: 4592 | N12: 0 | O12: 229.6 | P12: 20 | Q12: 229.6 | R12: 4592 | S12: 20 | T12: 229.6 | U12: 4592 | V12: 0 | W12: 0 | X12: 0
A13: 2018 | B13: 3 | C13: 201803 | D13: Kelly Group | E13: 公隆化學股份有限公司 | F13: 88000426 | G13: 分散劑 HIPLAAD ED400 18KG/PAIL | H13: 0 | I13: 0 | J13: 0 | K13: 54 | L13: 1477.5185 | M13: 79786 | N13: 0 | O13: 1477.5185 | P13: 54 | Q13: 1477.5185 | R13: 79786 | S13: 54 | T13: 1477.5185 | U13: 79786 | V13: 0 | W13: 0 | X13: 0
... A110: 2018 | B110: 5 | C110: 201805 | D110: Kelly Group | E110: 公隆化學股份有限公司 | F110: 87100033 | G110: 產品87100033 | H110: 0 | I110: 0 | J110: 0 | K110: 17 | L110: 1211.2353 | M110: 20591 | N110: 0 | O110: 1211.2353 | P110: 17 | Q110: 1211.2353 | R110: 20591 | S110: 17 | T110: 1211.2353 | U110: 20591 | V110: 0 | W110: 0 | X110: 0
